Workbook

Sheet CATALOGO FERIA
A1: INVENTARIO LA TABA
A2: Catálogo de muebles y objetos
D3: ACTUALIZADO: | E3: 24/09/2026
A5: Imagen | B5: Objeto | C5: Descripción | D5: Valor Nuevo | E5: Valor Usado
A6: Dormitorio 2
B7: Sommier 2 Plazas | C7: Sommier en buen estado | E7: 350000
B8: Respaldo negro | C8: Respaldo negro en perfecto estado | E8: 60000
B9: Mesa de luz Blanca | C9: Comoda con cajon blanca | E9: 50000
B10: Mesa de luz Blanca | C10: Comoda con cajon blanca | E10: 50000
B11: Velador artesanal — x2 | C11: Velador artesanal | E11: 100000
B12: Cuadro caballo blanco | C12: Cuadro caballo grande | E12: 100000
B13: Cuna + Cambiador + Cajonera | C13: Cuna con colchon, cambiador y cajones | E13: 250000
B14: Escritorio | C14: Escritorio blanco con cajones | E14: 120000
B15: Sillon Matero de un cuerpo | C15: Un cuerpo color beige | E15: 150000
B16: TV Admiral 32' | C16: TV 32' Admiral | E16: 150000
B17: Estufa electrica ATMA | C17: Estufa atma con ruedas | E17: 120000
A18: Dormitorio 3
B19: Mesa de luz blanca | C19: Comoda con cajon blanca | E19: 50000
B20: Velador artesanal | C20: Velador artesanal | E20: 50000
A21: Sin ambiente informado
A22: AGREGAR FOTO
A23: Dormitorio 4
A24: AGREGAR FOTO | B24: Mesa de luz blanca | C24: Comoda con cajon blanca | E24: 50000
B25: Velador artesanal | C25: Velador artesanal de hierro con campana | E25: 100000
B26: Cuadro Conejo | C26: Cuadro conejo | E26: 50000
B27: Cama de Hierro negro 1 Plaza + colchon — x2 | C27: cama de hierro negro mas colchon en buen estado | E27: 200000
A28: Dormitorio 5
B29: Mesa de luz blanca — x2 | C29: Comoda con cajon blanca | E29: 100000
B30: Sommier 2 Plazas | C30: Sommier 2P en buen estado | E30: 350000
B31: Velador artesanal | C31: Velador artesanal | E31: 50000
B32: Estufa electrica ATMA | C32: Estufa atma con ruedas | E32: 120000
B33: Aplique de pared rustico | C33: Aplique de pared con tirador | E33: 100000
A34: Dormitorio 6
B35: Cama de madera 1 Plaza — x2 | C35: Cama de madera 1 Plaza con respaldo | E35: 200000
B36: Mesa de luz Blanca chica | C36: Mesa de luz blanca chica | E36: 35000
B37: Velador artesanal | C37: Velador artesanal | E37: 50000
B38: Cuadro oveja | C38: Cuadro de oveja | E38: 50000
A39: Dormitorio 7
B40: Cama de madera 1 Plaza — x2 | C40: Cama de madera 1 Plaza con respaldo | E40: 200000
B41: Mesa de luz blanca | C41: Mesa de luz blanca con cajon | E41: 50000
B42: Velador artesanal | C42: Velador artesanal de hierro con campana | E42: 50000
B43: Cuadro vaca | C43: Cuadro de vaca marco de madera | E43: 50000
A44: Dormitorio 8
B45: Cama de madera 1 plaza con camastro y 3 cajones | C45: Cama de 1 plaza con camastro y 3 cajones | E45: 200000
B46: Cama de hierro 1 Plaza | C46: Cama con base de hierro 1 Plaza | E46: 120000
B47: Cofre de madera blanco | C47: Cofre de madera | E47: 50000
B48: Cuadro oveja | C48: Cuadro de oveja marco de madera | E48: 50000
A49: Living altillo
B50: Sillon cama verde | C50: Sillon cama verde plegable | E50: 120000
B51: Sillon cama amarillo | C51: Sillon cama amarillo plegable | E51: 150000
B52: Mesa ratona de madera | C52: Mesa ratona de madera | E52: 80000
B53: Cuadro caballos amanecer | C53: Cuadro caballos amanecer | E53: 100000
A54: Dormitorio 9
B55: Sommier 2 Plazas | C55: Cama sommier 2 Plazas | E55: 350000
B56: Respaldo 2 Plazas negro | C56: Respaldo negro en perfecto estado | E56: 60000
B57: Mesa de luz blanca | C57: Mesa de luz blanca con cajon | E57: 50000
B58: Mesa de luz blanca | C58: Mesa de luz blanca con cajon | E58: 50000
B59: Velador artesanal | C59: Velador artesanal de hierro con campana | E59: 50000
B60: Velador artesanal | C60: Velador artesanal de hierro con campana | E60: 50000
B61: Cuadro caballo | C61: Cuadro de caballo blanco | E61: 100000
B62: Sillon matero de un cuerpo | C62: Sillon matero rojo 1 cuerpo | E62: 150000
A63: Dormitorio 10
B64: Sommier 2 Plazas | C64: Cama sommier 2 Plazas | E64: 350000
B65: Mesa de luz Blanca — x2 | C65: Mesa de luz blanca con cajon | E65: 50000
B66: Velador artesanal — x2 | C66: Velador artesanal de hierro con campana | E66: 50000
B67: Respaldo 2 Plazas negro | C67: Respaldo negro en perfecto estado | E67: 60000
B68: Cuadro caballos amanecer | C68: Cuadro caballos amanecer | E68: 100000
A69: Dormitorio principal
B70: Sommier 2 Plazas | C70: Cama sommier 2 Plazas | E70: 350000
B71: Respaldo 2 Plazas negro | C71: Respaldo negro en perfecto estado | E71: 60000
B72: Mesa de luz | C72: Mesa de luz blanca con cajon | E72: 35000
B73: Mesa de luz | C73: Mesa de luz blanca con cajon | E73: 50000
B74: Velador artesanal — x2 | C74: Velador artesanal de hierro con campana | E74: 200000
B75: Cuadro caballo | C75: Cuadro de caballo | E75: 100000
B76: Sillon matero gris | C76: Sillon matero gris 1 cuerpo | E76: 150000
B77: Estufa electrica ATMA — x2 | C77: Estufa atma con ruedas | E77: 200000
A78: Living secundario
B79: Cama de mimbre y colchon | C79: Cama de mimbre con colchon | E79: 100000
B80: Sillon cama azul | C80: Sillon cama azul | E80: 200000
B81: Mesa de madera chica | C81: Mesa ratona de madera | E81: 100000
B82: Velador de pie | C82: Velador de pie | E82: 30000
B83: Cuadro caballo | C83: Cuadro de caballos | E83: 100000
A84: Living principal
B85: Sillon 3 cuerpos cuero | C85: Sillon 3 cuerpos cuero marron | E85: 200000
B86: Sillon 1 cuerpo cuero — x2 | C86: Sillon 1 cuerpo cuero marron | E86: 200000
B87: Perchero de madera | C87: Perchero de madera 5 | E87: 30000
A88: AGREGAR FOTO | B88: Cuadro caballo — x6 | C88: Multiples cuadros de caballos | E88: 600000
B89: Mesa ratona de vidrio | C89: Mesa ratona cuadrada de vidrio | E89: 100000
A90: Salon de juegos
B91: Sillones 2 cuerpos azul — x3 | C91: Sillon azul dos cuerpos | E91: 1000000
A92: AGREGAR FOTO | B92: Mesa ratona de madera | C92: Mesa ratona de madera | E92: 200000
B93: Mesa de ping pong | C93: Mesa de ping pong | E93: 400000
B94: Metegol | C94: Metegol | E94: 100000
B95: Lampara de pie | C95: Lampara de pie | E95: 30000
B96: Mueble rustico | C96: Mueble de madera rustico | E96: 150000
A97: Sin ambiente informado
A98: AGREGAR FOTO
A99: Resibidor
B100: Sillon 3 cuerpos floreado | C100: Sillon 3 cuerpos floreado | E100: 200000
B101: Perchero de madera largo | C101: Perchero de madera 10 | E101: 50000
...

Sheet RESUMEN
B2: INVENTARIO — ESTANCIA LA TABA
B4: INDICADORES GENERALES | E4: CONTROL DE VENTA | H4: ORDEN DE RELEVAMIENTO
B5: Registros cargados | C5: =COUNTIF(INVENTARIO!A2:A1000,"<>") -> 138 | E5: Valor publicado vendido ($) | F5: =C15 -> 0 | H5: 1. Recorrer un ambiente completo antes de pasar al siguiente.
B6: Unidades totales | C6: =SUM(INVENTARIO!F2:F1000) -> 540 | E6: Valor publicado pendiente ($) | F6: =C13-C15 -> 50880000 | H6: 2. Asignar un ID único a cada artículo o lote.
B7: Disponibles | C7: =COUNTIF(INVENTARIO!J2:J1000,"Disponible") -> 126 | E7: Porcentaje de unidades vendidas | F7: =IFERROR(COUNTIF(INVENTARIO!J2:J1000,"Vendido")/COUNTIF(INVENTARIO!A2:A1000,"<>"),0) -> 0 | H7: 3. Fotografiar cada pieza y nombrar las fotos con su ID.
B8: Reservados | C8: =COUNTIF(INVENTARIO!J2:J1000,"Reservado") -> 0 | H8: 4. Medir muebles grandes y anotar desperfectos.
B9: Vendidos | C9: =COUNTIF(INVENTARIO!J2:J1000,"Vendido") -> 0 | H9: 5. Marcar el nivel de valor: Alto / Medio / Bajo.
B10: Retirados | C10: =COUNTIF(INVENTARIO!J2:J1000,"Retirado") -> 0 | H10: 6. Definir si se publica en el catálogo.
B11: No vender | C11: =COUNTIF(INVENTARIO!J2:J1000,"No vender") -> 0 | H11: 7. Colocar una etiqueta física con el ID y precio.
B12: Publicados | C12: =COUNTIF(INVENTARIO!K2:K1000,"Sí") -> 125 | H12: 8. Durante la feria actualizar Estado de venta y datos del comprador.
B13: Valor total publicado ($) | C13: =SUMPRODUCT(INVENTARIO!F2:F1000,INVENTARIO!I2:I1000) -> 50880000
B14: Valor publicado disponible ($) | C14: =SUMPRODUCT((INVENTARIO!J2:J1000="Disponible")*INVENTARIO!F2:F1000*INVENTARIO!I2:I1000) -> 45010000
B15: Valor publicado vendido ($) | C15: =SUMPRODUCT((INVENTARIO!J2:J1000="Vendido")*INVENTARIO!F2:F1000*INVENTARIO!I2:I1000) -> 0
B18: RESUMEN POR AMBIENTE
B19: Ambiente | C19: Registros | D19: Vendidos | E19: Disponibles | F19: Valor publicado
B20: Casco / Casa principal | C20: =COUNTIF(INVENTARIO!B2:B1000,B20) -> 0 | D20: =COUNTIFS(INVENTARIO!B2:B1000,B20,INVENTARIO!J2:J1000,"Vendido") -> 0 | E20: =COUNTIFS(INVENTARIO!B2:B1000,B20,INVENTARIO!J2:J1000,"Disponible") -> 0 | F20: =SUMPRODUCT((INVENTARIO!B2:B1000=B20)*INVENTARIO!F2:F1000*INVENTARIO!I2:I1000) -> 0
B21: Living principal | C21: =COUNTIF(INVENTARIO!B2:B1000,B21) -> 5 | D21: =COUNTIFS(INVENTARIO!B2:B1000,B21,INVENTARIO!J2:J1000,"Vendido") -> 0 | E21: =COUNTIFS(INVENTARIO!B2:B1000,B21,INVENTARIO!J2:J1000,"Disponible") -> 5 | F21: =SUMPRODUCT((INVENTARIO!B2:B1000=B21)*INVENTARIO!F2:F1000*INVENTARIO!I2:I1000) -> 4330000
B22: Living secundario | C22: =COUNTIF(INVENTARIO!B2:B1000,B22) -> 5 | D22: =COUNTIFS(INVENTARIO!B2:B1000,B22,INVENTARIO!J2:J1000,"Vendido") -> 0 | E22: =COUNTIFS(INVENTARIO!B2:B1000,B22,INVENTARIO!J2:J1000,"Disponible") -> 5 | F22: =SUMPRODUCT((INVENTARIO!B2:B1000=B22)*INVENTARIO!F2:F1000*INVENTARIO!I2:I1000) -> 530000
B23: Comedor principal | C23: =COUNTIF(INVENTARIO!B2:B1000,B23) -> 3 | D23: =COUNTIFS(INVENTARIO!B2:B1000,B23,INVENTARIO!J2:J1000,"Vendido") -> 0 | E23: =COUNTIFS(INVENTARIO!B2:B1000,B23,INVENTARIO!J2:J1000,"Disponible") -> 3 | F23: =SUMPRODUCT((INVENTARIO!B2:B1000=B23)*INVENTARIO!F2:F1000*INVENTARIO!I2:I1000) -> 1000000
B24: Comedor secundario | C24: =COUNTIF(INVENTARIO!B2:B1000,B24) -> 0 | D24: =COUNTIFS(INVENTARIO!B2:B1000,B24,INVENTARIO!J2:J1000,"Vendido") -> 0 | E24: =COUNTIFS(INVENTARIO!B2:B1000,B24,INVENTARIO!J2:J1000,"Disponible") -> 0 | F24: =SUMPRODUCT((INVENTARIO!B2:B1000=B24)*INVENTARIO!F2:F1000*INVENTARIO!I2:I1000) -> 0
B25: Cocina | C25: =COUNTIF(INVENTARIO!B2:B1000,B25) -> 24 | D25: =COUNTIFS(INVENTARIO!B2:B1000,B25,INVENTARIO!J2:J1000,"Vendido") -> 0 | E25: =COUNTIFS(INVENTARIO!B2:B1000,B25,INVENTARIO!J2:J1000,"Disponible") -> 24 | F25: =SUMPRODUCT((INVENTARIO!B2:B1000=B25)*INVENTARIO!F2:F1000*INVENTARIO!I2:I1000) -> 23205000
B26: Dormitorio principal | C26: =COUNTIF(INVENTARIO!B2:B1000,B26) -> 8 | D26: =COUNTIFS(INVENTARIO!B2:B1000,B26,INVENTARIO!J2:J1000,"Vendido") -> 0 | E26: =COUNTIFS(INVENTARIO!B2:B1000,B26,INVENTARIO!J2:J1000,"Disponible") -> 8 | F26: =SUMPRODUCT((INVENTARIO!B2:B1000=B26)*INVENTARIO!F2:F1000*INVENTARIO!I2:I1000) -> 1545000
B27: Dormitorio 2 | C27: =COUNTIF(INVENTARIO!B2:B1000,B27) -> 11 | D27: =COUNTIFS(INVENTARIO!B2:B1000,B27,INVENTARIO!J2:J1000,"Vendido") -> 0 | E27: =COUNTIFS(INVENTARIO!B2:B1000,B27,INVENTARIO!J2:J1000,"Disponible") -> 11 | F27: =SUMPRODUCT((INVENTARIO!B2:B1000=B27)*INVENTARIO!F2:F1000*INVENTARIO!I2:I1000) -> 1600000
B28: Dormitorio 3 | C28: =COUNTIF(INVENTARIO!B2:B1000,B28) -> 2 | D28: =COUNTIFS(INVENTARIO!B2:B1000,B28,INVENTARIO!J2:J1000,"Vendido") -> 0 | E28: =COUNTIFS(INVENTARIO!B2:B1000,B28,INVENTARIO!J2:J1000,"Disponible") -> 2 | F28: =SUMPRODUCT((INVENTARIO!B2:B1000=B28)*INVENTARIO!F2:F1000*INVENTARIO!I2:I1000) -> 100000
B29: Dormitorio 4 | C29: =COUNTIF(INVENTARIO!B2:B1000,B29) -> 4 | D29: =COUNTIFS(INVENTARIO!B2:B1000,B29,INVENTARIO!J2:J1000,"Vendido") -> 0 | E29: =COUNTIFS(INVENTARIO!B2:B1000,B29,INVENTARIO!J2:J1000,"Disponible") -> 4 | F29: =SUMPRODUCT((INVENTARIO!B2:B1000=B29)*INVENTARIO!F2:F1000*INVENTARIO!I2:I1000) -> 150000
B30: Dormitorio 5 | C30: =COUNTIF(INVENTARIO!B2:B1000,B30) -> 5 | D30: =COUNTIFS(INVENTARIO!B2:B1000,B30,INVENTARIO!J2:J1000,"Vendido") -> 0 | E30: =COUNTIFS(INVENTARIO!B2:B1000,B30,INVENTARIO!J2:J1000,"Disponible") -> 5 | F30: =SUMPRODUCT((INVENTARIO!B2:B1000=B30)*INVENTARIO!F2:F1000*INVENTARIO!I2:I1000) -> 820000
B31: Dormitorio 6 | C31: =COUNTIF(INVENTARIO!B2:B1000,B31) -> 4 | D31: =COUNTIFS(INVENTARIO!B2:B1000,B31,INVENTARIO!J2:J1000,"Vendido") -> 0 | E31: =COUNTIFS(INVENTARIO!B2:B1000,B31,INVENTARIO!J2:J1000,"Disponible") -> 4 | F31: =SUMPRODUCT((INVENTARIO!B2:B1000=B31)*INVENTARIO!F2:F1000*INVENTARIO!I2:I1000) -> 535000
B32: Dormitorio 7 | C32: =COUNTIF(INVENTARIO!B2:B1000,B32) -> 4 | D32: =COUNTIFS(INVENTARIO!B2:B1000,B32,INVENTARIO!J2:J1000,"Vendido") -> 0 | E32: =COUNTIFS(INVENTARIO!B2:B1000,B32,INVENTARIO!J2:J1000,"Disponible") -> 4 | F32: =SUMPRODUCT((INVENTARIO!B2:B1000=B32)*INVENTARIO!F2:F1000*INVENTARIO!I2:I1000) -> 550000
B33: Dormitorio 8 | C33: =COUNTIF(INVENTARIO!B2:B1000,B33) -> 4 | D33: =COUNTIFS(INVENTARIO!B2:B1000,B33,INVENTARIO!J2:J1000,"Vendido") -> 0 | E33: =COUNTIFS(INVENTARIO!B2:B1000,B33,INVENTARIO!J2:J1000,"Disponible") -> 4 | F33: =SUMPRODUCT((INVENTARIO!B2:B1000=B33)*INVENTARIO!F2:F1000*INVENTARIO!I2:I1000) -> 420000
B34: Dormitorio 9 | C34: =COUNTIF(INVENTARIO!B2:B1000,B34) -> 8 | D34: =COUNTIFS(INVENTARIO!B2:B1000,B34,INVENTARIO!J2:J1000,"Vendido") -> 0 | E34: =COUNTIFS(INVENTARIO!B2:B1000,B34,INVENTARIO!J2:J1000,"Disponible") -> 8 | F34: =SUMPRODUCT((INVENTARIO!B2:B1000=B34)*INVENTARIO!F2:F1000*INVENTARIO!I2:I1000) -> 860000
B35: Dormitorio 10 | C35: =COUNTIF(INVENTARIO!B2:B1000,B35) -> 5 | D35: =COUNTIFS(INVENTARIO!B2:B1000,B35,INVENTARIO!J2:J1000,"Vendido") -> 0 | E35: =COUNTIFS(INVENTARIO!B2:B1000,B35,INVENTARIO!J2:J1000,"Disponible") -> 5 | F35: =SUMPRODUCT((INVENTARIO!B2:B1000=B35)*INVENTARIO!F2:F1000*INVENTARIO!I2:I1000) -> 710000
B36: Baño 1 | C36: =COUNTIF(INVENTARIO!B2:B1000,B36) -> 0 | D36: =COUNTIFS(INVENTARIO!B2:B1000,B36,INVENTARIO!J2:J1000,"Vendido") -> 0 | E36: =COUNTIFS(INVENTARIO!B2:B1000,B36,INVENTARIO!J2:J1000,"Disponible") -> 0 | F36: =SUMPRODUCT((INVENTARIO!B2:B1000=B36)*INVENTARIO!F2:F1000*INVENTARIO!I2:I1000) -> 0
B37: Baño 2 | C37: =COUNTIF(INVENTARIO!B2:B1000,B37) -> 0 | D37: =COUNTIFS(INVENTARIO!B2:B1000,B37,INVENTARIO!J2:J1000,"Vendido") -> 0 | E37: =COUNTIFS(INVENTARIO!B2:B1000,B37,INVENTARIO!J2:J1000,"Disponible") -> 0 | F37: =SUMPRODUCT((INVENTARIO!B2:B1000=B37)*INVENTARIO!F2:F1000*INVENTARIO!I2:I1000) -> 0
B38: Baño 3 | C38: =COUNTIF(INVENTARIO!B2:B1000,B38) -> 0 | D38: =COUNTIFS(INVENTARIO!B2:B1000,B38,INVENTARIO!J2:J1000,"Vendido") -> 0 | E38: =COUNTIFS(INVENTARIO!B2:B1000,B38,INVENTARIO!J2:J1000,"Disponible") -> 0 | F38: =SUMPRODUCT((INVENTARIO!B2:B1000=B38)*INVENTARIO!F2:F1000*INVENTARIO!I2:I1000) -> 0
B39: Baño 4 | C39: =COUNTIF(INVENTARIO!B2:B1000,B39) -> 0 | D39: =COUNTIFS(INVENTARIO!B2:B1000,B39,INVENTARIO!J2:J1000,"Vendido") -> 0 | E39: =COUNTIFS(INVENTARIO!B2:B1000,B39,INVENTARIO!J2:J1000,"Disponible") -> 0 | F39: =SUMPRODUCT((INVENTARIO!B2:B1000=B39)*INVENTARIO!F2:F1000*INVENTARIO!I2:I1000) -> 0
B40: Baño 5 | C40: =COUNTIF(INVENTARIO!B2:B1000,B40) -> 0 | D40: =COUNTIFS(INVENTARIO!B2:B1000,B40,INVENTARIO!J2:J1000,"Vendido") -> 0 | E40: =COUNTIFS(INVENTARIO!B2:B1000,B40,INVENTARIO!J2:J1000,"Disponible") -> 0 | F40: =SUMPRODUCT((INVENTARIO!B2:B1000=B40)*INVENTARIO!F2:F1000*INVENTARIO!I2:I1000) -> 0
B41: Baño 6 | C41: =COUNTIF(INVENTARIO!B2:B1000,B41) -> 0 | D41: =COUNTIFS(INVENTARIO!B2:B1000,B41,INVENTARIO!J2:J1000,"Vendido") -> 0 | E41: =COUNTIFS(INVENTARIO!B2:B1000,B41,INVENTARIO!J2:J1000,"Disponible") -> 0 | F41: =SUMPRODUCT((INVENTARIO!B2:B1000=B41)*INVENTARIO!F2:F1000*INVENTARIO!I2:I1000) -> 0
B42: Baño 7 | C42: =COUNTIF(INVENTARIO!B2:B1000,B42) -> 0 | D42: =COUNTIFS(INVENTARIO!B2:B1000,B42,INVENTARIO!J2:J1000,"Vendido") -> 0 | E42: =COUNTIFS(INVENTARIO!B2:B1000,B42,INVENTARIO!J2:J1000,"Disponible") -> 0 | F42: =SUMPRODUCT((INVENTARIO!B2:B1000=B42)*INVENTARIO!F2:F1000*INVENTARIO!I2:I1000) -> 0
B43: Baño 8 | C43: =COUNTIF(INVENTARIO!B2:B1000,B43) -> 0 | D43: =COUNTIFS(INVENTARIO!B2:B1000,B43,INVENTARIO!J2:J1000,"Vendido") -> 0 | E43: =COUNTIFS(INVENTARIO!B2:B1000,B43,INVENTARIO!J2:J1000,"Disponible") -> 0 | F43: =SUMPRODUCT((INVENTARIO!B2:B1000=B43)*INVENTARIO!F2:F1000*INVENTARIO!I2:I1000) -> 0
B44: Galería | C44: =COUNTIF(INVENTARIO!B2:B1000,B44) -> 2 | D44: =COUNTIFS(INVENTARIO!B2:B1000,B44,INVENTARIO!J2:J1000,"Vendido") -> 0 | E44: =COUNTIFS(INVENTARIO!B2:B1000,B44,INVENTARIO!J2:J1000,"Disponible") -> 2 | F44: =SUMPRODUCT((INVENTARIO!B2:B1000=B44)*INVENTARIO!F2:F1000*INVENTARIO!I2:I1000) -> 1000000
B45: Quincho | C45: =COUNTIF(INVENTARIO!B2:B1000,B45) -> 0 | D45: =COUNTIFS(INVENTARIO!B2:B1000,B45,INVENTARIO!J2:J1000,"Vendido") -> 0 | E45: =COUNTIFS(INVENTARIO!B2:B1000,B45,INVENTARIO!J2:J1000,"Disponible") -> 0 | F45: =SUMPRODUCT((INVENTARIO!B2:B1000=B45)*INVENTARIO!F2:F1000*INVENTARIO!I2:I1000) -> 0
B46: Parrilla | C46: =COUNTIF(INVENTARIO!B2:B1000,B46) -> 0 | D46: =COUNTIFS(INVENTARIO!B2:B1000,B46,INVENTARIO!J2:J1000,"Vendido") -> 0 | E46: =COUNTIFS(INVENTARIO!B2:B1000,B46,INVENTARIO!J2:J1000,"Disponible") -> 0 | F46: =SUMPRODUCT((INVENTARIO!B2:B1000=B46)*INVENTARIO!F2:F1000*INVENTARIO!I2:I1000) -> 0
B47: Pileta | C47: =COUNTIF(INVENTARIO!B2:B1000,B47) -> 0 | D47: =COUNTIFS(INVENTARIO!B2:B1000,B47,INVENTARIO!J2:J1000,"Vendido") -> 0 | E47: =COUNTIFS(INVENTARIO!B2:B1000,B47,INVENTARIO!J2:J1000,"Disponible") -> 0 | F47: =SUMPRODUCT((INVENTARIO!B2:B1000=B47)*INVENTARIO!F2:F1000*INVENTARIO!I2:I1000) -> 0
B48: Jardín / Parque | C48: =COUNTIF(INVENTARIO!B2:B1000,B48) -> 3 | D48: =COUNTIFS(INVENTARIO!B2:B1000,B48,INVENTARIO!J2:J1000,"Vendido") -> 0 | E48: =COUNTIFS(INVENTARIO!B2:B1000,B48,INVENTARIO!J2:J1000,"Disponible") -> 0 | F48: =SUMPRODUCT((INVENTARIO!B2:B1000=B48)*INVENTARIO!F2:F1000*INVENTARIO!I2:I1000) -> 1000000
B49: Garage | C49: =COUNTIF(INVENTARIO!B2:B1000,B49) -> 0 | D49: =COUNTIFS(INVENTARIO!B2:B1000,B49,INVENTARIO!J2:J1000,"Vendido") -> 0 | E49: =COUNTIFS(INVENTARIO!B2:B1000,B49,INVENTARIO!J2:J1000,"Disponible") -> 0 | F49: =SUMPRODUCT((INVENTARIO!B2:B1000=B49)*INVENTARIO!F2:F1000*INVENTARIO!I2:I1000) -> 0
B50: Depósito | C50: =COUNTIF(INVENTARIO!B2:B1000,B50) -> 0 | D50: =COUNTIFS(INVENTARIO!B2:B1000,B50,INVENTARIO!J2:J1000,"Vendido") -> 0 | E50: =COUNTIFS(INVENTARIO!B2:B1000,B50,INVENTARIO!J2:J1000,"Disponible") -> 0 | F50: =SUMPRODUCT((INVENTARIO!B2:B1000=B50)*INVENTARIO!F2:F1000*INVENTARIO!I2:I1000) -> 0
B51: Lavadero | C51: =COUNTIF(INVENTARIO!B2:B1000,B51) -> 12 | D51: =COUNTIFS(INVENTARIO!B2:B1000,B51,INVENTARIO!J2:J1000,"Vendido") -> 0 | E51: =COUNTIFS(INVENTARIO!B2:B1000,B51,INVENTARIO!J2:J1000,"Disponible") -> 12 | F51: =SUMPRODUCT((INVENTARIO!B2:B1000=B51)*INVENTARIO!F2:F1000*INVENTARIO!I2:I1000) -> 1450000
B52: Pasillo / Distribuidor | C52: =COUNTIF(INVENTARIO!B2:B1000,B52) -> 0 | D52: =COUNTIFS(INVENTARIO!B2:B1000,B52,INVENTARIO!J2:J1000,"Vendido") -> 0 | E52: =COUNTIFS(INVENTARIO!B2:B1000,B52,INVENTARIO!J2:J1000,"Disponible") -> 0 | F52: =SUMPRODUCT((INVENTARIO!B2:B1000=B52)*INVENTARIO!F2:F1000*INVENTARIO!I2:I1000) -> 0
B53: Exterior | C53: =COUNTIF(INVENTARIO!B2:B1000,B53) -> 0 | D53: =COUNTIFS(INVENTARIO!B2:B1000,B53,INVENTARIO!J2:J1000,"Vendido") -> 0 | E53: =COUNTIFS(INVENTARIO!B2:B1000,B53,INVENTARIO!J2:J1000,"Disponible") -> 0 | F53: =SUMPRODUCT((INVENTARIO!B2:B1000=B53)*INVENTARIO!F2:F1000*INVENTARIO!I2:I1000) -> 0
B54: Otro | C54: =COUNTIF(INVENTARIO!B2:B1000,B54) -> 0 | D54: =COUNTIFS(INVENTARIO!B2:B1000,B54,INVENTARIO!J2:J1000,"Vendido") -> 0 | E54: =COUNTIFS(INVENTARIO!B2:B1000,B54,INVENTARIO!J2:J1000,"Disponible") -> 0 | F54: =SUMPRODUCT((INVENTARIO!B2:B1000=B54)*INVENTARIO!F2:F1000*INVENTARIO!I2:I1000) -> 0
A57: CONTABILIDAD DE OBJETOS
A58: Objeto | B58: Cantidad | C58: =COUNTIF(INVENTARIO!B2:B1000,B58) -> 0 | D58: =COUNTIFS(INVENTARIO!B2:B1000,B58,INVENTARIO!J2:J1000,"Vendido") -> 0 | E58: =COUNTIFS(INVENTARIO!B2:B1000,B58,INVENTARIO!J2:J1000,"Disponible") -> 0 | F58: =SUMPRODUCT((INVENTARIO!B2:B1000=B58)*INVENTARIO!F2:F1000*INVENTARIO!I2:I1000) -> 0
A59: 1 fuente | B59: 1 | C59: =COUNTIF(INVENTARIO!B2:B1000,B59) -> 0 | D59: =COUNTIFS(INVENTARIO!B2:B1000,B59,INVENTARIO!J2:J1000,"Vendido") -> 0 | E59: =COUNTIFS(INVENTARIO!B2:B1000,B59,INVENTARIO!J2:J1000,"Disponible") -> 0 | F59: =SUMPRODUCT((INVENTARIO!B2:B1000=B59)*INVENTARIO!F2:F1000*INVENTARIO!I2:I1000) -> 0
A60: 2 bancos de madera coloniales | B60: 2 | C60: =COUNTIF(INVENTARIO!B2:B1000,B60) -> 0 | D60: =COUNTIFS(INVENTARIO!B2:B1000,B60,INVENTARIO!J2:J1000,"Vendido") -> 0 | E60: =COUNTIFS(INVENTARIO!B2:B1000,B60,INVENTARIO!J2:J1000,"Disponible") -> 0 | F60: =SUMPRODUCT((INVENTARIO!B2:B1000=B60)*INVENTARIO!F2:F1000*INVENTARIO!I2:I1000) -> 0
A61: 2 banquetas de madera | B61: 2 | C61: =COUNTIF(INVENTARIO!B2:B1000,B61) -> 0 | D61: =COUNTIFS(INVENTARIO!B2:B1000,B61,INVENTARIO!J2:J1000,"Vendido") -> 0 | E61: =COUNTIFS(INVENTARIO!B2:B1000,B61,INVENTARIO!J2:J1000,"Disponible") -> 0 | F61: =SUMPRODUCT((INVENTARIO!B2:B1000=B61)*INVENTARIO!F2:F1000*INVENTARIO!I2:I1000) -> 0
A62: 4 bancos de madera | B62: 4 | C62: =COUNTIF(INVENTARIO!B2:B1000,B62) -> 0 | D62: =COUNTIFS(INVENTARIO!B2:B1000,B62,INVENTARIO!J2:J1000,"Vendido") -> 0 | E62: =COUNTIFS(INVENTARIO!B2:B1000,B62,INVENTARIO!J2:J1000,"Disponible") -> 0 | F62: =SUMPRODUCT((INVENTARIO!B2:B1000=B62)*INVENTARIO!F2:F1000*INVENTARIO!I2:I1000) -> 0
A63: 4 fuentes de asado | B63: 4 | C63: =COUNTIF(INVENTARIO!B2:B1000,B63) -> 0 | D63: =COUNTIFS(INVENTARIO!B2:B1000,B63,INVENTARIO!J2:J1000,"Vendido") -> 0 | E63: =COUNTIFS(INVENTARIO!B2:B1000,B63,INVENTARIO!J2:J1000,"Disponible") -> 0 | F63: =SUMPRODUCT((INVENTARIO!B2:B1000=B63)*INVENTARIO!F2:F1000*INVENTARIO!I2:I1000) -> 0
A64: alfombra ducha | B64: 4 | C64: =COUNTIF(INVENTARIO!B2:B1000,B64) -> 0 | D64: =COUNTIFS(INVENTARIO!B2:B1000,B64,INVENTARIO!J2:J1000,"Vendido") -> 0 | E64: =COUNTIFS(INVENTARIO!B2:B1000,B64,INVENTARIO!J2:J1000,"Disponible") -> 0 | F64: =SUMPRODUCT((INVENTARIO!B2:B1000=B64)*INVENTARIO!F2:F1000*INVENTARIO!I2:I1000) -> 0
A65: aplique de pared rustico | B65: 1 | C65: =COUNTIF(INVENTARIO!B2:B1000,B65) -> 0 | D65: =COUNTIFS(INVENTARIO!B2:B1000,B65,INVENTARIO!J2:J1000,"Vendido") -> 0 | E65: =COUNTIFS(INVENTARIO!B2:B1000,B65,INVENTARIO!J2:J1000,"Disponible") -> 0 | F65: =SUMPRODUCT((INVENTARIO!B2:B1000=B65)*INVENTARIO!F2:F1000*INVENTARIO!I2:I1000) -> 0
A66: banquetas barra | B66: 3 | C66: =COUNTIF(INVENTARIO!B2:B1000,B66) -> 0 | D66: =COUNTIFS(INVENTARIO!B2:B1000,B66,INVENTARIO!J2:J1000,"Vendido") -> 0 | E66: =COUNTIFS(INVENTARIO!B2:B1000,B66,INVENTARIO!J2:J1000,"Disponible") -> 0 | F66: =SUMPRODUCT((INVENTARIO!B2:B1000=B66)*INVENTARIO!F2:F1000*INVENTARIO!I2:I1000) -> 0
A67: cafetera lilana | B67: 1 | C67: =COUNTIF(INVENTARIO!B2:B1000,B67) -> 0 | D67: =COUNTIFS(INVENTARIO!B2:B1000,B67,INVENTARIO!J2:J1000,"Vendido") -> 0 | E67: =COUNTIFS(INVENTARIO!B2:B1000,B67,INVENTARIO!J2:J1000,"Disponible") -> 0 | F67: =SUMPRODUCT((INVENTARIO!B2:B1000=B67)*INVENTARIO!F2:F1000*INVENTARIO!I2:I1000) -> 0
A68: cama de hierro 1 plaza | B68: 1 | C68: =COUNTIF(INVENTARIO!B2:B1000,B68) -> 0 | D68: =COUNTIFS(INVENTARIO!B2:B1000,B68,INVENTARIO!J2:J1000,"Vendido") -> 0 | E68: =COUNTIFS(INVENTARIO!B2:B1000,B68,INVENTARIO!J2:J1000,"Disponible") -> 0 | F68: =SUMPRODUCT((INVENTARIO!B2:B1000=B68)*INVENTARIO!F2:F1000*INVENTARIO!I2:I1000) -> 0
A69: cama de hierro negro 1 plaza + colchon | B69: 2 | C69: =COUNTIF(INVENTARIO!B2:B1000,B69) -> 0 | D69: =COUNTIFS(INVENTARIO!B2:B1000,B69,INVENTARIO!J2:J1000,"Vendido") -> 0 | E69: =COUNTIFS(INVENTARIO!B2:B1000,B69,INVENTARIO!J2:J1000,"Disponible") -> 0 | F69: =SUMPRODUCT((INVENTARIO!B2:B1000=B69)*INVENTARIO!F2:F1000*INVENTARIO!I2:I1000) -> 0
A70: cama de madera 1 plaza | B70: 4 | C70: =COUNTIF(INVENTARIO!B2:B1000,B70) -> 0 | D70: =COUNTIFS(INVENTARIO!B2:B1000,B70,INVENTARIO!J2:J1000,"Vendido") -> 0 | E70: =COUNTIFS(INVENTARIO!B2:B1000,B70,INVENTARIO!J2:J1000,"Disponible") -> 0 | F70: =SUMPRODUCT((INVENTARIO!B2:B1000=B70)*INVENTARIO!F2:F1000*INVENTARIO!I2:I1000) -> 0
A71: cama de madera 1 plaza con camastro y 3 cajones | B71: 1 | C71: =COUNTIF(INVENTARIO!B2:B1000,B71) -> 0 | D71: =COUNTIFS(INVENTARIO!B2:B1000,B71,INVENTARIO!J2:J1000,"Vendido") -> 0 | E71: =COUNTIFS(INVENTARIO!B2:B1000,B71,INVENTARIO!J2:J1000,"Disponible") -> 0 | F71: =SUMPRODUCT((INVENTARIO!B2:B1000=B71)*INVENTARIO!F2:F1000*INVENTARIO!I2:I1000) -> 0
A72: cama de mimbre y colchon | B72: 1 | C72: =COUNTIF(INVENTARIO!B2:B1000,B72) -> 0 | D72: =COUNTIFS(INVENTARIO!B2:B1000,B72,INVENTARIO!J2:J1000,"Vendido") -> 0 | E72: =COUNTIFS(INVENTARIO!B2:B1000,B72,INVENTARIO!J2:J1000,"Disponible") -> 0 | F72: =SUMPRODUCT((INVENTARIO!B2:B1000=B72)*INVENTARIO!F2:F1000*INVENTARIO!I2:I1000) -> 0
A73: cofre de madera blanco | B73: 1 | C73: =COUNTIF(INVENTARIO!B2:B1000,B73) -> 0 | D73: =COUNTIFS(INVENTARIO!B2:B1000,B73,INVENTARIO!J2:J1000,"Vendido") -> 0 | E73: =COUNTIFS(INVENTARIO!B2:B1000,B73,INVENTARIO!J2:J1000,"Disponible") -> 0 | F73: =SUMPRODUCT((INVENTARIO!B2:B1000=B73)*INVENTARIO!F2:F1000*INVENTARIO!I2:I1000) -> 0
A74: colchoneta vieja | B74: 1 | C74: =COUNTIF(INVENTARIO!B2:B1000,B74) -> 0 | D74: =COUNTIFS(INVENTARIO!B2:B1000,B74,INVENTARIO!J2:J1000,"Vendido") -> 0 | E74: =COUNTIFS(INVENTARIO!B2:B1000,B74,INVENTARIO!J2:J1000,"Disponible") -> 0 | F74: =SUMPRODUCT((INVENTARIO!B2:B1000=B74)*INVENTARIO!F2:F1000*INVENTARIO!I2:I1000) -> 0
A75: copas de agua | B75: 40 | C75: =COUNTIF(INVENTARIO!B2:B1000,B75) -> 0 | D75: =COUNTIFS(INVENTARIO!B2:B1000,B75,INVENTARIO!J2:J1000,"Vendido") -> 0 | E75: =COUNTIFS(INVENTARIO!B2:B1000,B75,INVENTARIO!J2:J1000,"Disponible") -> 0 | F75: =SUMPRODUCT((INVENTARIO!B2:B1000=B75)*INVENTARIO!F2:F1000*INVENTARIO!I2:I1000) -> 0
A76: cuadro caballo | B76: 10 | C76: =COUNTIF(INVENTARIO!B2:B1000,B76) -> 0 | D76: =COUNTIFS(INVENTARIO!B2:B1000,B76,INVENTARIO!J2:J1000,"Vendido") -> 0 | E76: =COUNTIFS(INVENTARIO!B2:B1000,B76,INVENTARIO!J2:J1000,"Disponible") -> 0 | F76: =SUMPRODUCT((INVENTARIO!B2:B1000=B76)*INVENTARIO!F2:F1000*INVENTARIO!I2:I1000) -> 0
A77: cuadro caballo blanco | B77: 1 | C77: =COUNTIF(INVENTARIO!B2:B1000,B77) -> 0 | D77: =COUNTIFS(INVENTARIO!B2:B1000,B77,INVENTARIO!J2:J1000,"Vendido") -> 0 | E77: =COUNTIFS(INVENTARIO!B2:B1000,B77,INVENTARIO!J2:J1000,"Disponible") -> 0 | F77: =SUMPRODUCT((INVENTARIO!B2:B1000=B77)*INVENTARIO!F2:F1000*INVENTARIO!I2:I1000) -> 0
A78: cuadro caballos amanecer | B78: 2 | C78: =COUNTIF(INVENTARIO!B2:B1000,B78) -> 0 | D78: =COUNTIFS(INVENTARIO!B2:B1000,B78,INVENTARIO!J2:J1000,"Vendido") -> 0 | E78: =COUNTIFS(INVENTARIO!B2:B1000,B78,INVENTARIO!J2:J1000,"Disponible") -> 0 | F78: =SUMPRODUCT((INVENTARIO!B2:B1000=B78)*INVENTARIO!F2:F1000*INVENTARIO!I2:I1000) -> 0
A79: cuadro conejo | B79: 1 | C79: =COUNTIF(INVENTARIO!B2:B1000,B79) -> 0 | D79: =COUNTIFS(INVENTARIO!B2:B1000,B79,INVENTARIO!J2:J1000,"Vendido") -> 0 | E79: =COUNTIFS(INVENTARIO!B2:B1000,B79,INVENTARIO!J2:J1000,"Disponible") -> 0 | F79: =SUMPRODUCT((INVENTARIO!B2:B1000=B79)*INVENTARIO!F2:F1000*INVENTARIO!I2:I1000) -> 0
A80: cuadro oveja | B80: 2 | C80: =COUNTIF(INVENTARIO!B2:B1000,B80) -> 0 | D80: =COUNTIFS(INVENTARIO!B2:B1000,B80,INVENTARIO!J2:J1000,"Vendido") -> 0 | E80: =COUNTIFS(INVENTARIO!B2:B1000,B80,INVENTARIO!J2:J1000,"Disponible") -> 0 | F80: =SUMPRODUCT((INVENTARIO!B2:B1000=B80)*INVENTARIO!F2:F1000*INVENTARIO!I2:I1000) -> 0
A81: cuadro vaca | B81: 1 | C81: =COUNTIF(INVENTARIO!B2:B1000,B81) -> 0 | D81: =COUNTIFS(INVENTARIO!B2:B1000,B81,INVENTARIO!J2:J1000,"Vendido") -> 0 | E81: =COUNTIFS(INVENTARIO!B2:B1000,B81,INVENTARIO!J2:J1000,"Disponible") -> 0 | F81: =SUMPRODUCT((INVENTARIO!B2:B1000=B81)*INVENTARIO!F2:F1000*INVENTARIO!I2:I1000) -> 0
A82: cubiertos | B82: 125 | C82: =COUNTIF(INVENTARIO!B2:B1000,B82) -> 0 | D82: =COUNTIFS(INVENTARIO!B2:B1000,B82,INVENTARIO!J2:J1000,"Vendido") -> 0 | E82: =COUNTIFS(INVENTARIO!B2:B1000,B82,INVENTARIO!J2:J1000,"Disponible") -> 0 | F82: =SUMPRODUCT((INVENTARIO!B2:B1000=B82)*INVENTARIO!F2:F1000*INVENTARIO!I2:I1000) -> 0
A83: cuna + cambiador + cajonera | B83: 1 | C83: =COUNTIF(INVENTARIO!B2:B1000,B83) -> 0 | D83: =COUNTIFS(INVENTARIO!B2:B1000,B83,INVENTARIO!J2:J1000,"Vendido") -> 0 | E83: =COUNTIFS(INVENTARIO!B2:B1000,B83,INVENTARIO!J2:J1000,"Disponible") -> 0 | F83: =SUMPRODUCT((INVENTARIO!B2:B1000=B83)*INVENTARIO!F2:F1000*INVENTARIO!I2:I1000) -> 0
A84: escritorio | B84: 1 | C84: =COUNTIF(INVENTARIO!B2:B1000,B84) -> 0 | D84: =COUNTIFS(INVENTARIO!B2:B1000,B84,INVENTARIO!J2:J1000,"Vendido") -> 0 | E84: =COUNTIFS(INVENTARIO!B2:B1000,B84,INVENTARIO!J2:J1000,"Disponible") -> 0 | F84: =SUMPRODUCT((INVENTARIO!B2:B1000=B84)*INVENTARIO!F2:F1000*INVENTARIO!I2:I1000) -> 0
A85: estufa electrica atma | B85: 4 | C85: =COUNTIF(INVENTARIO!B2:B1000,B85) -> 0 | D85: =COUNTIFS(INVENTARIO!B2:B1000,B85,INVENTARIO!J2:J1000,"Vendido") -> 0 | E85: =COUNTIFS(INVENTARIO!B2:B1000,B85,INVENTARIO!J2:J1000,"Disponible") -> 0 | F85: =SUMPRODUCT((INVENTARIO!B2:B1000=B85)*INVENTARIO!F2:F1000*INVENTARIO!I2:I1000) -> 0
A86: frizzer whirlpool | B86: 1 | C86: =COUNTIF(INVENTARIO!B2:B1000,B86) -> 0 | D86: =COUNTIFS(INVENTARIO!B2:B1000,B86,INVENTARIO!J2:J1000,"Vendido") -> 0 | E86: =COUNTIFS(INVENTARIO!B2:B1000,B86,INVENTARIO!J2:J1000,"Disponible") -> 0 | F86: =SUMPRODUCT((INVENTARIO!B2:B1000=B86)*INVENTARIO!F2:F1000*INVENTARIO!I2:I1000) -> 0
A87: fuentes de vidrio | B87: 5 | C87: =COUNTIF(INVENTARIO!B2:B1000,B87) -> 0 | D87: =COUNTIFS(INVENTARIO!B2:B1000,B87,INVENTARIO!J2:J1000,"Vendido") -> 0 | E87: =COUNTIFS(INVENTARIO!B2:B1000,B87,INVENTARIO!J2:J1000,"Disponible") -> 0 | F87: =SUMPRODUCT((INVENTARIO!B2:B1000=B87)*INVENTARIO!F2:F1000*INVENTARIO!I2:I1000) -> 0
A88: heladera lg | B88: 1 | C88: =COUNTIF(INVENTARIO!B2:B1000,B88) -> 0 | D88: =COUNTIFS(INVENTARIO!B2:B1000,B88,INVENTARIO!J2:J1000,"Vendido") -> 0 | E88: =COUNTIFS(INVENTARIO!B2:B1000,B88,INVENTARIO!J2:J1000,"Disponible") -> 0 | F88: =SUMPRODUCT((INVENTARIO!B2:B1000=B88)*INVENTARIO!F2:F1000*INVENTARIO!I2:I1000) -> 0
A89: heladera philco | B89: 1 | C89: =COUNTIF(INVENTARIO!B2:B1000,B89) -> 0 | D89: =COUNTIFS(INVENTARIO!B2:B1000,B89,INVENTARIO!J2:J1000,"Vendido") -> 0 | E89: =COUNTIFS(INVENTARIO!B2:B1000,B89,INVENTARIO!J2:J1000,"Disponible") -> 0 | F89: =SUMPRODUCT((INVENTARIO!B2:B1000=B89)*INVENTARIO!F2:F1000*INVENTARIO!I2:I1000) -> 0
A90: jarras de plastico | B90: 2 | C90: =COUNTIF(INVENTARIO!B2:B1000,B90) -> 0 | D90: =COUNTIFS(INVENTARIO!B2:B1000,B90,INVENTARIO!J2:J1000,"Vendido") -> 0 | E90: =COUNTIFS(INVENTARIO!B2:B1000,B90,INVENTARIO!J2:J1000,"Disponible") -> 0 | F90: =SUMPRODUCT((INVENTARIO!B2:B1000=B90)*INVENTARIO!F2:F1000*INVENTARIO!I2:I1000) -> 0
A91: jarras de vidrio | B91: 3 | C91: =COUNTIF(INVENTARIO!B2:B1000,B91) -> 0 | D91: =COUNTIFS(INVENTARIO!B2:B1000,B91,INVENTARIO!J2:J1000,"Vendido") -> 0 | E91: =COUNTIFS(INVENTARIO!B2:B1000,B91,INVENTARIO!J2:J1000,"Disponible") -> 0 | F91: =SUMPRODUCT((INVENTARIO!B2:B1000=B91)*INVENTARIO!F2:F1000*INVENTARIO!I2:I1000) -> 0
A92: juego de casita y hamaca | B92: 1 | C92: =COUNTIF(INVENTARIO!B2:B1000,B92) -> 0 | D92: =COUNTIFS(INVENTARIO!B2:B1000,B92,INVENTARIO!J2:J1000,"Vendido") -> 0 | E92: =COUNTIFS(INVENTARIO!B2:B1000,B92,INVENTARIO!J2:J1000,"Disponible") -> 0 | F92: =SUMPRODUCT((INVENTARIO!B2:B1000=B92)*INVENTARIO!F2:F1000*INVENTARIO!I2:I1000) -> 0
A93: juego hamacas y tobogan nuevo | B93: 1 | C93: =COUNTIF(INVENTARIO!B2:B1000,B93) -> 0 | D93: =COUNTIFS(INVENTARIO!B2:B1000,B93,INVENTARIO!J2:J1000,"Vendido") -> 0 | E93: =COUNTIFS(INVENTARIO!B2:B1000,B93,INVENTARIO!J2:J1000,"Disponible") -> 0 | F93: =SUMPRODUCT((INVENTARIO!B2:B1000=B93)*INVENTARIO!F2:F1000*INVENTARIO!I2:I1000) -> 0
A94: lampara de pie | B94: 1 | C94: =COUNTIF(INVENTARIO!B2:B1000,B94) -> 0 | D94: =COUNTIFS(INVENTARIO!B2:B1000,B94,INVENTARIO!J2:J1000,"Vendido") -> 0 | E94: =COUNTIFS(INVENTARIO!B2:B1000,B94,INVENTARIO!J2:J1000,"Disponible") -> 0 | F94: =SUMPRODUCT((INVENTARIO!B2:B1000=B94)*INVENTARIO!F2:F1000*INVENTARIO!I2:I1000) -> 0
A95: lavarrolas eslabon de lujo | B95: 1 | C95: =COUNTIF(INVENTARIO!B2:B1000,B95) -> 0 | D95: =COUNTIFS(INVENTARIO!B2:B1000,B95,INVENTARIO!J2:J1000,"Vendido") -> 0 | E95: =COUNTIFS(INVENTARIO!B2:B1000,B95,INVENTARIO!J2:J1000,"Disponible") -> 0 | F95: =SUMPRODUCT((INVENTARIO!B2:B1000=B95)*INVENTARIO!F2:F1000*INVENTARIO!I2:I1000) -> 0
A96: lavarropas drean | B96: 3 | C96: =COUNTIF(INVENTARIO!B2:B1000,B96) -> 0 | D96: =COUNTIFS(INVENTARIO!B2:B1000,B96,INVENTARIO!J2:J1000,"Vendido") -> 0 | E96: =COUNTIFS(INVENTARIO!B2:B1000,B96,INVENTARIO!J2:J1000,"Disponible") -> 0 | F96: =SUMPRODUCT((INVENTARIO!B2:B1000=B96)*INVENTARIO!F2:F1000*INVENTARIO!I2:I1000) -> 0
A97: lavarropas lg | B97: 1 | C97: =COUNTIF(INVENTARIO!B2:B1000,B97) -> 0 | D97: =COUNTIFS(INVENTARIO!B2:B1000,B97,INVENTARIO!J2:J1000,"Vendido") -> 0 | E97: =COUNTIFS(INVENTARIO!B2:B1000,B97,INVENTARIO!J2:J1000,"Disponible") -> 0 | F97: =SUMPRODUCT((INVENTARIO!B2:B1000=B97)*INVENTARIO!F2:F1000*INVENTARIO!I2:I1000) -> 0
A98: mesa de apoyo de madera | B98: 1 | C98: =COUNTIF(INVENTARIO!B2:B1000,B98) -> 0 | D98: =COUNTIFS(INVENTARIO!B2:B1000,B98,INVENTARIO!J2:J1000,"Vendido") -> 0 | E98: =COUNTIFS(INVENTARIO!B2:B1000,B98,INVENTARIO!J2:J1000,"Disponible") -> 0 | F98: =SUMPRODUCT((INVENTARIO!B2:B1000=B98)*INVENTARIO!F2:F1000*INVENTARIO!I2:I1000) -> 0
A99: mesa de hierro negra | B99: 1 | C99: =COUNTIF(INVENTARIO!B2:B1000,B99) -> 0 | D99: =COUNTIFS(INVENTARIO!B2:B1000,B99,INVENTARIO!J2:J1000,"Vendido") -> 0 | E99: =COUNTIFS(INVENTARIO!B2:B1000,B99,INVENTARIO!J2:J1000,"Disponible") -> 0 | F99: =SUMPRODUCT((INVENTARIO!B2:B1000=B99)*INVENTARIO!F2:F1000*INVENTARIO!I2:I1000) -> 0
A100: mesa de luz | B100: 2 | C100: =COUNTIF(INVENTARIO!B2:B1000,B100) -> 0 | D100: =COUNTIFS(INVENTARIO!B2:B1000,B100,INVENTARIO!J2:J1000,"Vendido") -> 0 | E100: =COUNTIFS(INVENTARIO!B2:B1000,B100,INVENTARIO!J2:J1000,"Disponible") -> 0 | F100: =SUMPRODUCT((INVENTARIO!B2:B1000=B100)*INVENTARIO!F2:F1000*INVENTARIO!I2:I1000) -> 0
A101: mesa de luz blanca | B101: 11 | C101: =COUNTIF(INVENTARIO!B2:B1000,B101) -> 0 | D101: =COUNTIFS(INVENTARIO!B2:B1000,B101,INVENTARIO!J2:J1000,"Vendido") -> 0 | E101: =COUNTIFS(INVENTARIO!B2:B1000,B101,INVENTARIO!J2:J1000,"Disponible") -> 0 | F101: =SUMPRODUCT((INVENTARIO!B2:B1000=B101)*INVENTARIO!F2:F1000*INVENTARIO!I2:I1000) -> 0
A102: mesa de luz blanca chica | B102: 1 | C102: =COUNTIF(INVENTARIO!B2:B1000,B102) -> 0 | D102: =COUNTIFS(INVENTARIO!B2:B1000,B102,INVENTARIO!J2:J1000,"Vendido") -> 0 | E102: =COUNTIFS(INVENTARIO!B2:B1000,B102,INVENTARIO!J2:J1000,"Disponible") -> 0 | F102: =SUMPRODUCT((INVENTARIO!B2:B1000=B102)*INVENTARIO!F2:F1000*INVENTARIO!I2:I1000) -> 0
A103: mesa de madera chica | B103: 1 | C103: =COUNTIF(INVENTARIO!B2:B1000,B103) -> 0 | D103: =COUNTIFS(INVENTARIO!B2:B1000,B103,INVENTARIO!J2:J1000,"Vendido") -> 0 | E103: =COUNTIFS(INVENTARIO!B2:B1000,B103,INVENTARIO!J2:J1000,"Disponible") -> 0 | F103: =SUMPRODUCT((INVENTARIO!B2:B1000=B103)*INVENTARIO!F2:F1000*INVENTARIO!I2:I1000) -> 0
A104: mesa de madera grande 14 sillas | B104: 1 | C104: =COUNTIF(INVENTARIO!B2:B1000,B104) -> 0 | D104: =COUNTIFS(INVENTARIO!B2:B1000,B104,INVENTARIO!J2:J1000,"Vendido") -> 0 | E104: =COUNTIFS(INVENTARIO!B2:B1000,B104,INVENTARIO!J2:J1000,"Disponible") -> 0 | F104: =SUMPRODUCT((INVENTARIO!B2:B1000=B104)*INVENTARIO!F2:F1000*INVENTARIO!I2:I1000) -> 0
A105: mesa de ping pong | B105: 1 | C105: =COUNTIF(INVENTARIO!B2:B1000,B105) -> 0 | D105: =COUNTIFS(INVENTARIO!B2:B1000,B105,INVENTARIO!J2:J1000,"Vendido") -> 0 | E105: =COUNTIFS(INVENTARIO!B2:B1000,B105,INVENTARIO!J2:J1000,"Disponible") -> 0 | F105: =SUMPRODUCT((INVENTARIO!B2:B1000=B105)*INVENTARIO!F2:F1000*INVENTARIO!I2:I1000) -> 0
A106: mesa de vidrio y ratan | B106: 1 | C106: =COUNTIF(INVENTARIO!B2:B1000,B106) -> 0 | D106: =COUNTIFS(INVENTARIO!B2:B1000,B106,INVENTARIO!J2:J1000,"Vendido") -> 0 | E106: =COUNTIFS(INVENTARIO!B2:B1000,B106,INVENTARIO!J2:J1000,"Disponible") -> 0 | F106: =SUMPRODUCT((INVENTARIO!B2:B1000=B106)*INVENTARIO!F2:F1000*INVENTARIO!I2:I1000) -> 0
...

Sheet INVENTARIO
A1: ID | B1: Ambiente | C1: Categoría | D1: Artículo | E1: Descripción | F1: Cantidad | G1: Medidas | H1: Estado | I1: Precio publicado | J1: Estado de venta | K1: Publicar | L1: Foto principal (insertar en celda) | M1: Fotos adicionales
A2: EST-001 | B2: Dormitorio 2 | C2: Muebles | D2: Sommier 2 Plazas | E2: Sommier en buen estado | F2: 1 | G2: 2 Plazas | I2: 350000 | J2: Disponible | K2: Sí | L2: EST-001.jpg
A3: EST-002 | B3: Dormitorio 2 | C3: Muebles | D3: Respaldo negro | E3: Respaldo negro en perfecto estado | F3: 1 | G3: 2 Plazas | H3: Buen estado | I3: 60000 | J3: Disponible | K3: Sí | L3: EST-002.jpg
A4: EST-003 | B4: Dormitorio 2 | C4: Muebles | D4: Mesa de luz Blanca | E4: Comoda con cajon blanca | F4: 1 | G4: 43x31x65 | H4: Buen estado | I4: 50000 | J4: Disponible | K4: Sí | L4: EST-003.jpg
A5: EST-004 | B5: Dormitorio 2 | C5: Muebles | D5: Mesa de luz Blanca | E5: Comoda con cajon blanca | F5: 1 | G5: 43x31x65 | H5: Despintada | I5: 50000 | J5: Disponible | K5: Sí | L5: EST-004.jpg
A6: EST-005 | B6: Dormitorio 2 | C6: Iluminacion | D6: Velador artesanal | E6: Velador artesanal | F6: 2 | H6: Buen estado | I6: 100000 | J6: Disponible | K6: Sí | L6: EST-005.jpg
A7: EST-006 | B7: Dormitorio 2 | C7: Cuadros caballos | D7: Cuadro caballo blanco | E7: Cuadro caballo grande | F7: 1 | H7: Buen estado | I7: 100000 | J7: Disponible | K7: Sí | L7: EST-006.jpg
A8: EST-007 | B8: Dormitorio 2 | C8: Muebles | D8: Cuna + Cambiador + Cajonera | E8: Cuna con colchon, cambiador y cajones | F8: 1 | H8: Sin detalles | I8: 250000 | J8: Disponible | K8: Sí | L8: EST-007.jpg
A9: EST-008 | B9: Dormitorio 2 | C9: Muebles | D9: Escritorio | E9: Escritorio blanco con cajones | F9: 1 | H9: Buen estado | I9: 120000 | J9: Disponible | K9: Sí | L9: EST-008.jpg
A10: EST-009 | B10: Dormitorio 2 | C10: Muebles | D10: Sillon Matero de un cuerpo | E10: Un cuerpo color beige | F10: 1 | H10: Buen estado | I10: 150000 | J10: Disponible | K10: Sí | L10: EST-009.jpg
A11: EST-010 | B11: Dormitorio 2 | C11: Electrodimesticos | D11: TV Admiral 32' | E11: TV 32' Admiral | F11: 1 | G11: 32' | H11: Buen estado | I11: 150000 | J11: Disponible | K11: Sí | L11: EST-010.jpg
A12: EST-011 | B12: Dormitorio 2 | C12: Electrodimesticos | D12: Estufa electrica ATMA | E12: Estufa atma con ruedas | F12: 1 | H12: Buen estado | I12: 120000 | J12: Disponible | K12: Sí | L12: EST-011.jpg
A13: EST-012 | B13: Dormitorio 3 | C13: Muebles | D13: Mesa de luz blanca | E13: Comoda con cajon blanca | F13: 1 | G13: 43x31x65 | H13: Buen estado | I13: 50000 | J13: Disponible | K13: Sí | L13: EST-012.jpg
A14: EST-013 | B14: Dormitorio 3 | C14: Iluminacion | D14: Velador artesanal | E14: Velador artesanal | F14: 1 | H14: Buen estado | I14: 50000 | J14: Disponible | K14: Sí | L14: EST-013.jpg
A15: EST-014 | J15: Disponible | K15: Sí
A16: EST-015 | B16: Dormitorio 4 | C16: Muebles | D16: Mesa de luz blanca | E16: Comoda con cajon blanca | F16: 1 | G16: 43x31x65 | H16: Buen estado | I16: 50000 | J16: Disponible | K16: Sí | L16: EST-015.jpg
A17: EST-016 | B17: Dormitorio 4 | C17: Iluminacion | D17: Velador artesanal | E17: Velador artesanal de hierro con campana | F17: 1 | H17: Buen estado | I17: 100000 | J17: Disponible | K17: Sí | L17: EST-016.jpg
A18: EST-017 | B18: Dormitorio 4 | C18: Cuadro animales | D18: Cuadro Conejo | E18: Cuadro conejo | F18: 1 | H18: Buen estado | J18: Disponible | K18: Sí
A19: EST-018 | B19: Dormitorio 4 | C19: Muebles | D19: Cama de Hierro negro 1 Plaza + colchon | E19: cama de hierro negro mas colchon en buen estado | F19: 2 | G19: 1 Plaza | H19: Buen estado | J19: Disponible | K19: Sí
A20: EST-019 | B20: Dormitorio 5 | C20: Muebles | D20: Mesa de luz blanca | E20: Comoda con cajon blanca | F20: 2 | G20: 43x31x65 | H20: Buen estado | I20: 100000 | J20: Disponible | K20: Sí
A21: EST-020 | B21: Dormitorio 5 | C21: Muebles | D21: Sommier 2 Plazas | E21: Sommier 2P en buen estado | F21: 1 | G21: 2 Plazas | H21: Buen estado | I21: 350000 | J21: Disponible | K21: Sí
A22: EST-021 | B22: Dormitorio 5 | C22: Iluminacion | D22: Velador artesanal | E22: Velador artesanal | F22: 1 | H22: Buen estado | I22: 50000 | J22: Disponible | K22: Sí
A23: EST-022 | B23: Dormitorio 5 | C23: Electrodimesticos | D23: Estufa electrica ATMA | E23: Estufa atma con ruedas | F23: 1 | H23: Buen estado | I23: 120000 | J23: Disponible | K23: Sí
A24: EST-023 | B24: Dormitorio 5 | C24: Iluminacion | D24: Aplique de pared rustico | E24: Aplique de pared con tirador | F24: 1 | H24: Buen estado | I24: 100000 | J24: Disponible | K24: Sí
A25: EST-024 | B25: Dormitorio 6 | C25: Muebles | D25: Cama de madera 1 Plaza | E25: Cama de madera 1 Plaza con respaldo | F25: 2 | G25: 1 Plaza | H25: Buen estado | I25: 200000 | J25: Disponible | K25: Sí
A26: EST-025 | B26: Dormitorio 6 | C26: Muebles | D26: Mesa de luz Blanca chica | E26: Mesa de luz blanca chica | F26: 1 | G26: 35x30x60 | H26: Despintada | I26: 35000 | J26: Disponible | K26: Sí
A27: EST-026 | B27: Dormitorio 6 | C27: Iluminacion | D27: Velador | E27: Velador artesanal | F27: 1 | H27: Buen estado | I27: 50000 | J27: Disponible | K27: Sí
A28: EST-027 | B28: Dormitorio 6 | C28: Cuadro animales | D28: Cuadro oveja | E28: Cuadro de oveja | F28: 1 | H28: Buen estado | I28: 50000 | J28: Disponible | K28: Sí
A29: EST-028 | B29: Dormitorio 7 | C29: Muebles | D29: Cama de madera 1 Plaza | E29: Cama de madera 1 Plaza con respaldo | F29: 2 | G29: 1 Plaza | H29: Buen estado | I29: 200000 | J29: Disponible | K29: Sí
A30: EST-029 | B30: Dormitorio 7 | C30: Muebles | D30: Mesa de luz blanca | E30: Mesa de luz blanca con cajon | F30: 1 | G30: 43x31x65 | H30: Buen estado | I30: 50000 | J30: Disponible | K30: Sí
A31: EST-030 | B31: Dormitorio 7 | C31: Iluminacion | D31: Velador artesanal | E31: Velador artesanal de hierro con campana | F31: 1 | H31: Buen estado | I31: 50000 | J31: Disponible | K31: Sí
A32: EST-031 | B32: Dormitorio 7 | C32: Cuadro animales | D32: Cuadro vaca | E32: Cuadro de vaca marco de madera | F32: 1 | H32: Buen estado | I32: 50000 | J32: Disponible | K32: Sí
A33: EST-032 | B33: Dormitorio 8 | C33: Muebles | D33: Cama de madera 1 plaza con camastro y 3 cajones | E33: Cama de 1 plaza con camastro y 3 cajones | F33: 1 | G33: 1 Plaza | H33: Buen estado | I33: 200000 | J33: Disponible | K33: Sí
A34: EST-033 | B34: Dormitorio 8 | C34: Muebles | D34: Cama de hierro 1 Plaza | E34: Cama con base de hierro 1 Plaza | F34: 1 | G34: 1 Plaza | H34: Buen estado | I34: 120000 | J34: Disponible | K34: Sí
A35: EST-034 | B35: Dormitorio 8 | C35: Muebles | D35: Cofre de madera blanco | E35: Cofre de madera | F35: 1 | G35: 50x50x50 | H35: Buen estado | I35: 50000 | J35: Disponible | K35: Sí
A36: EST-035 | B36: Dormitorio 8 | C36: Cuadro animales | D36: Cuadro oveja | E36: Cuadro de oveja marco de madera | F36: 1 | H36: Buen estado | I36: 50000 | J36: Disponible | K36: Sí
A37: EST-036 | B37: Living altillo | C37: Muebles | D37: Sillon cama verde | E37: Sillon cama verde plegable | F37: 1 | H37: Roto pero funcional | I37: 120000 | J37: Disponible | K37: Sí
A38: EST-037 | B38: Living altillo | C38: Muebles | D38: Sillon cama amarillo | E38: Sillon cama amarillo plegable | F38: 1 | H38: Buen estado | I38: 150000 | J38: Disponible | K38: Sí
A39: EST-038 | B39: Living altillo | C39: Muebles | D39: Mesa ratona de madera | E39: Mesa ratona de madera | F39: 1 | G39: 100x60x40 | H39: Buen estado | I39: 80000 | J39: Disponible | K39: Sí
A40: EST-039 | B40: Living altillo | C40: Cuadros caballos | D40: Cuadro caballos amanecer | E40: Cuadro caballos amanecer | F40: 1 | H40: Buen estado | I40: 100000 | J40: Disponible | K40: Sí
A41: EST-040 | B41: Dormitorio 9 | C41: Muebles | D41: Sommier 2 Plazas | E41: Cama sommier 2 Plazas | F41: 1 | G41: 2 Plazas | H41: Buen estado | I41: 350000 | J41: Disponible | K41: Sí
A42: EST-041 | B42: Dormitorio 9 | C42: Muebles | D42: Respaldo 2 Plazas negro | E42: Respaldo negro en perfecto estado | F42: 1 | G42: 2 Plazas | H42: Buen estado | I42: 60000 | J42: Disponible | K42: Sí
A43: EST-042 | B43: Dormitorio 9 | C43: Muebles | D43: Mesa de luz blanca | E43: Mesa de luz blanca con cajon | F43: 1 | G43: 43x31x65 | H43: Buen estado | I43: 50000 | J43: Disponible | K43: Sí
A44: EST-043 | B44: Dormitorio 9 | C44: Muebles | D44: Mesa de luz blanca | E44: Mesa de luz blanca con cajon | F44: 1 | G44: 43x31x65 | H44: Buen estado | I44: 50000 | J44: Disponible | K44: Sí
A45: EST-044 | B45: Dormitorio 9 | C45: Iluminacion | D45: Velador artesanal | E45: Velador artesanal de hierro con campana | F45: 1 | H45: Buen estado | I45: 50000 | J45: Disponible | K45: Sí
A46: EST-045 | B46: Dormitorio 9 | C46: Iluminacion | D46: Velador artesanal | E46: Velador artesanal de hierro con campana | F46: 1 | H46: Buen estado | I46: 50000 | J46: Disponible | K46: Sí
A47: EST-046 | B47: Dormitorio 9 | C47: Cuadros caballos | D47: Cuadro caballo | E47: Cuadro de caballo blanco | F47: 1 | H47: Buen estado | I47: 100000 | J47: Disponible | K47: Sí
A48: EST-047 | B48: Dormitorio 9 | C48: Muebles | D48: Sillon matero de un cuerpo | E48: Sillon matero rojo 1 cuerpo | F48: 1 | H48: Buen estado | I48: 150000 | J48: Disponible | K48: Sí
A49: EST-048 | B49: Dormitorio 10 | C49: Muebles | D49: Sommier 2 Plazas | E49: Cama sommier 2 Plazas | F49: 1 | G49: 2 Plazas | H49: Buen estado | I49: 350000 | J49: Disponible | K49: Sí
A50: EST-049 | B50: Dormitorio 10 | C50: Muebles | D50: Mesa de luz Blanca | E50: Mesa de luz blanca con cajon | F50: 2 | G50: 43x31x65 | H50: Buen estado | I50: 50000 | J50: Disponible | K50: Sí
A51: EST-050 | B51: Dormitorio 10 | C51: Iluminacion | D51: Velador artesanal | E51: Velador artesanal de hierro con campana | F51: 2 | H51: Buen estado | I51: 50000 | J51: Disponible | K51: Sí
A52: EST-051 | B52: Dormitorio 10 | C52: Muebles | D52: Respaldo 2 Plazas negro | E52: Respaldo negro en perfecto estado | F52: 1 | G52: 2 Plazas | H52: Buen estado | I52: 60000 | J52: Disponible | K52: Sí
A53: EST-052 | B53: Dormitorio 10 | C53: Cuadros caballos | D53: Cuadro caballos amanecer | E53: Cuadro caballos amanecer | F53: 1 | H53: Buen estado | I53: 100000 | J53: Disponible | K53: Sí
A54: EST-053 | B54: Dormitorio principal | C54: Muebles | D54: Sommier 2 Plazas | E54: Cama sommier 2 Plazas | F54: 1 | G54: 2 Plazas | H54: Buen estado | I54: 350000 | J54: Disponible | K54: Sí
A55: EST-054 | B55: Dormitorio principal | C55: Muebles | D55: Respaldo 2 Plazas negro | E55: Respaldo negro en perfecto estado | F55: 1 | G55: 2 Plazas | H55: Buen estado | I55: 60000 | J55: Disponible | K55: Sí
A56: EST-055 | B56: Dormitorio principal | C56: Muebles | D56: Mesa de luz | E56: Mesa de luz blanca con cajon | F56: 1 | G56: 43x31x65 | H56: Despintada | I56: 35000 | J56: Disponible | K56: Sí
A57: EST-056 | B57: Dormitorio principal | C57: Muebles | D57: Mesa de luz | E57: Mesa de luz blanca con cajon | F57: 1 | G57: 43x31x66 | H57: Buen estado | I57: 50000 | J57: Disponible | K57: Sí
A58: EST-057 | B58: Dormitorio principal | C58: Iluminacion | D58: Velador artesanal | E58: Velador artesanal de hierro con campana | F58: 2 | H58: Buen estado | I58: 200000 | J58: Disponible | K58: Sí
A59: EST-058 | B59: Dormitorio principal | C59: Cuadros caballos | D59: Cuadro caballo | E59: Cuadro de caballo | F59: 1 | H59: Buen estado | I59: 100000 | J59: Disponible | K59: Sí
A60: EST-059 | B60: Dormitorio principal | C60: Muebles | D60: Sillon matero gris | E60: Sillon matero gris 1 cuerpo | F60: 1 | H60: Buen estado | I60: 150000 | J60: Disponible | K60: Sí
A61: EST-060 | B61: Dormitorio principal | C61: Electrodimesticos | D61: Estufa electrica ATMA | E61: Estufa atma con ruedas | F61: 2 | H61: Buen estado | I61: 200000 | J61: Disponible | K61: Sí
A62: EST-061 | B62: Living secundario | C62: Muebles | D62: Cama de mimbre y colchon | E62: Cama de mimbre con colchon | F62: 1 | G62: 1 Plaza | H62: Buen estado | I62: 100000 | J62: Disponible | K62: Sí
A63: EST-062 | B63: Living secundario | C63: Muebles | D63: Sillon cama azul | E63: Sillon cama azul | F63: 1 | G63: 2 M | H63: Buen estado | I63: 200000 | J63: Disponible | K63: Sí
A64: EST-063 | B64: Living secundario | C64: Muebles | D64: Mesa de madera chica | E64: Mesa ratona de madera | F64: 1 | G64: 90x1.50x38 | H64: Buen estado | I64: 100000 | J64: Disponible | K64: Sí
A65: EST-064 | B65: Living secundario | C65: Iluminacion | D65: Velador de pie | E65: Velador de pie | F65: 1 | H65: Probar devuelta no lo pude hacer funcionar | I65: 30000 | J65: Disponible | K65: Sí
A66: EST-065 | B66: Living secundario | C66: Cuadros caballos | D66: Cuadro caballo | E66: Cuadro de caballos | F66: 1 | H66: Buen estado | I66: 100000 | J66: Disponible | K66: Sí
A67: EST-066 | B67: Living principal | C67: Muebles | D67: Sillon 3 cuerpos cuero | E67: Sillon 3 cuerpos cuero marron | F67: 1 | G67: 2.10 M | H67: Pata rota cuero en buen estado | I67: 200000 | J67: Disponible | K67: Sí
A68: EST-067 | B68: Living principal | C68: Muebles | D68: Sillon 1 cuerpo cuero | E68: Sillon 1 cuerpo cuero marron | F68: 2 | G68: 1 cuerpo | H68: 1 roto en apoya brazo | I68: 200000 | J68: Disponible | K68: Sí
A69: EST-068 | B69: Living principal | C69: Muebles | D69: Perchero de madera | E69: Perchero de madera 5 | F69: 1 | G69: 60cm | H69: Buen estado | I69: 30000 | J69: Disponible | K69: Sí
A70: EST-069 | B70: Living principal | C70: Cuadros caballos | D70: Cuadro caballo | E70: Multiples cuadros de caballos | F70: 6 | H70: Buen estado | I70: 600000 | J70: Disponible | K70: Sí
A71: EST-070 | B71: Living principal | C71: Muebles | D71: Mesa ratona de vidrio | E71: Mesa ratona cuadrada de vidrio | F71: 1 | G71: 1x1 | H71: Buen estado | I71: 100000 | J71: Disponible | K71: Sí
A72: EST-071 | B72: Salon de juegos | C72: Muebles | D72: Sillones 2 cuerpos azul | E72: Sillon azul dos cuerpos | F72: 3 | G72: 2 cuerpos | H72: Buen estado | I72: 1000000 | J72: Disponible | K72: Sí
A73: EST-072 | B73: Salon de juegos | C73: Muebles | D73: Mesa ratona de madera | E73: Mesa ratona de madera | F73: 1 | G73: 1.40x83x50 | H73: Buen estado | I73: 200000 | J73: Disponible | K73: Sí
A74: EST-073 | B74: Salon de juegos | C74: Juegos | D74: Mesa de ping pong | E74: Mesa de ping pong | F74: 1 | G74: 2.73x1.53x75 | H74: Buen estado | I74: 400000 | J74: Disponible | K74: Sí
A75: EST-074 | B75: Salon de juegos | C75: Juegos | D75: Metegol | E75: Metegol | F75: 1 | H75: Buen estado | I75: 100000 | J75: Disponible | K75: Sí
A76: EST-075 | B76: Salon de juegos | C76: Iluminacion | D76: Lampara de pie | E76: Lampara de pie | F76: 1 | H76: Buen estado | I76: 30000 | J76: Disponible | K76: Sí
A77: EST-076 | B77: Salon de juegos | C77: Muebles | D77: Mueble rustico | E77: Mueble de madera rustico | F77: 1 | G77: 200x100x50 | H77: Buen estado | I77: 150000 | J77: Disponible | K77: Sí
A78: EST-078 | B78: Resibidor | C78: Muebles | D78: Sillon 3 cuerpos floreado | E78: Sillon 3 cuerpos floreado | F78: 1 | G78: 1.90x70 | H78: Buen estado | I78: 200000 | J78: Disponible | K78: Sí
A79: EST-079 | B79: Resibidor | C79: Muebles | D79: Perchero de madera largo | E79: Perchero de madera 10 | F79: 1 | G79: 1 M | H79: Buen estado | I79: 50000 | J79: Disponible | K79: Sí
A80: EST-080 | B80: Resibidor | C80: Cuadros caballos | D80: Cuadro caballo | E80: Cuadro caballo grande | F80: 1 | H80: Buen estado | I80: 100000 | J80: Disponible | K80: Sí
A81: EST-083 | B81: Comedor principal | C81: Muebles | D81: Mesa de madera grande 14 sillas | E81: Mesa de madera grande con 14 sillas | F81: 1 | G81: 3x1.20 | H81: Buen estado | I81: 400000 | J81: Disponible | K81: Sí
A82: EST-084 | B82: Comedor principal | C82: Muebles | D82: Mesa de apoyo de madera | E82: Mesa de apoyo de madera | F82: 1 | G82: 2x1 | H82: Buen estado | I82: 250000 | J82: Disponible | K82: Sí
A83: EST-085 | B83: Comedor principal | C83: Muebles | D83: Mueble de apoyo vintage | E83: Mueble de apoyo vintage | F83: 1 | G83: 1.5x2.3.65 | H83: Buen estado | I83: 350000 | J83: Disponible | K83: Sí
A84: EST-088 | B84: Sector Bar | C84: Muebles | D84: Mesa redonda madera grande | E84: Mesa redonda de madera | F84: 1 | G84: 1.20 | H84: Buen estado | I84: 200000 | J84: Disponible | K84: Sí
A85: EST-089 | B85: Sector Bar | C85: Muebles | D85: Sillas X5 | E85: Sillas de madera | F85: 5 | H85: Buen estado | I85: 100000 | J85: Disponible | K85: Sí
A86: EST-090 | B86: Sector Bar | C86: Muebles | D86: Banquetas barra | E86: Banquetas de madera barra | F86: 3 | H86: Buen estado | I86: 75000 | J86: Disponible | K86: Sí
A87: EST-091 | B87: Sector bar | C87: Estufa | D87: Tromen grande | E87: Tromen grande | F87: 1 | H87: Buen estado | I87: 600000 | J87: Disponible | K87: Sí
A88: EST-092 | J88: Disponible | K88: Sí
A89: EST-093 | J89: Disponible | K89: Sí
A90: EST-094 | B90: Lavadero | C90: Electrodimesticos | D90: Lavarropas LG | E90: Lavarropas LG 8.5KG | F90: 1 | G90: 60x57x85 | H90: Un poco oxidado funciona | I90: 450000 | J90: Disponible | K90: Sí
A91: EST-095 | B91: Lavadero | C91: Electrodimesticos | D91: Lavarropas Drean | E91: Lavarropas Drean 8.12KG | F91: 1 | G91: 60x55x85 | H91: Buen estado | I91: 250000 | J91: Disponible | K91: Sí
A92: EST-096 | B92: Lavadero | C92: Electrodimesticos | D92: Lavarropas Drean | E92: Lavarropas Drean 8.12KG | F92: 2 | G92: 60x55x85 | H92: Un poco oxidado funciona | I92: 250000 | J92: Disponible | K92: Sí
A93: EST-097 | B93: Lavadero | C93: Electrodimesticos | D93: Lavarrolas Eslabon de Lujo | E93: Lavarropas eslabon 7KG | F93: 1 | G93: 60x55x85 | H93: Buen estado | I93: 250000 | J93: Disponible | K93: Sí
A94: EST-098 | B94: Lavadero | C94: Electrodimesticos | D94: Secadora Philco | E94: Secadora fuera de servicio | F94: 1 | G94: 60x55x85 | H94: Buen estado | J94: Disponible | K94: Sí
A95: EST-099 | B95: Lavadero | C95: Textiles | D95: Sabanas blancas 1P | E95: Sabanas blancas 1P | F95: 48 | G95: 1 Plaza | H95: Buen estado | J95: Disponible | K95: Sí
A96: EST-100 | B96: Lavadero | C96: Textiles | D96: Sabanas blancas 2P | E96: Sabanas blancas 2P | F96: 24 | G96: 2 Plazas | H96: Buen estado | J96: Disponible | K96: Sí
A97: EST-101 | B97: Lavadero | C97: Textiles | D97: Toalla de mano | E97: Toallas de mano blancas | F97: 20 | H97: Buen estado | J97: Disponible | K97: Sí
A98: EST-102 | B98: Lavadero | C98: Textiles | D98: Sabanas de cuna | E98: Sabanas de cuna | F98: 2 | H98: Buen estado | J98: Disponible | K98: Sí
A99: EST-103 | B99: Lavadero | C99: Textiles | D99: Toallones blancos | E99: Toallones blancos | F99: 40 | H99: Buen estado | J99: Disponible | K99: Sí
A100: EST-104 | B100: Lavadero | C100: Textiles | D100: Repasadores | E100: Repasadores | F100: 23 | H100: Buen estado | J100: Disponible | K100: Sí
...

Sheet VENTAS
A1: ID | B1: Artículo | C1: Ambiente | D1: Tipo | E1: Precio publicado | F1: Precio vendido | G1: Diferencia | H1: Comprador | I1: Fecha | J1: Forma de pago | K1: Estado | L1: Observaciones
A2: =IF(INVENTARIO!A2="","",INVENTARIO!A2) -> EST-001 | B2: =IF(INVENTARIO!G2="","",INVENTARIO!G2) -> 2 Plazas | C2: =IF(INVENTARIO!B2="","",INVENTARIO!B2) -> Dormitorio 2 | D2: =IF(INVENTARIO!D2="","",INVENTARIO!D2) -> Sommier 2 Plazas | E2: =IF(INVENTARIO!O2="","",INVENTARIO!O2) | F2: =IF(INVENTARIO!Q2="","",INVENTARIO!Q2) | G2: =IF(OR(E2="",F2=""),"",E2-F2) | H2: =IF(INVENTARIO!T2="","",INVENTARIO!T2) | I2: =IF(INVENTARIO!U2="","",INVENTARIO!U2) | J2: =IF(INVENTARIO!V2="","",INVENTARIO!V2) | K2: =IF(INVENTARIO!R2="","",INVENTARIO!R2) | L2: =IF(INVENTARIO!Y2="","",INVENTARIO!Y2)
A3: =IF(INVENTARIO!A3="","",INVENTARIO!A3) -> EST-002 | B3: =IF(INVENTARIO!G3="","",INVENTARIO!G3) -> 2 Plazas | C3: =IF(INVENTARIO!B3="","",INVENTARIO!B3) -> Dormitorio 2 | D3: =IF(INVENTARIO!D3="","",INVENTARIO!D3) -> Respaldo negro | E3: =IF(INVENTARIO!O3="","",INVENTARIO!O3) | F3: =IF(INVENTARIO!Q3="","",INVENTARIO!Q3) | G3: =IF(OR(E3="",F3=""),"",E3-F3) | H3: =IF(INVENTARIO!T3="","",INVENTARIO!T3) | I3: =IF(INVENTARIO!U3="","",INVENTARIO!U3) | J3: =IF(INVENTARIO!V3="","",INVENTARIO!V3) | K3: =IF(INVENTARIO!R3="","",INVENTARIO!R3) | L3: =IF(INVENTARIO!Y3="","",INVENTARIO!Y3)
A4: =IF(INVENTARIO!A4="","",INVENTARIO!A4) -> EST-003 | B4: =IF(INVENTARIO!G4="","",INVENTARIO!G4) -> 43x31x65 | C4: =IF(INVENTARIO!B4="","",INVENTARIO!B4) -> Dormitorio 2 | D4: =IF(INVENTARIO!D4="","",INVENTARIO!D4) -> Mesa de luz Blanca | E4: =IF(INVENTARIO!O4="","",INVENTARIO!O4) | F4: =IF(INVENTARIO!Q4="","",INVENTARIO!Q4) | G4: =IF(OR(E4="",F4=""),"",E4-F4) | H4: =IF(INVENTARIO!T4="","",INVENTARIO!T4) | I4: =IF(INVENTARIO!U4="","",INVENTARIO!U4) | J4: =IF(INVENTARIO!V4="","",INVENTARIO!V4) | K4: =IF(INVENTARIO!R4="","",INVENTARIO!R4) | L4: =IF(INVENTARIO!Y4="","",INVENTARIO!Y4)
A5: =IF(INVENTARIO!A5="","",INVENTARIO!A5) -> EST-004 | B5: =IF(INVENTARIO!G5="","",INVENTARIO!G5) -> 43x31x65 | C5: =IF(INVENTARIO!B5="","",INVENTARIO!B5) -> Dormitorio 2 | D5: =IF(INVENTARIO!D5="","",INVENTARIO!D5) -> Mesa de luz Blanca | E5: =IF(INVENTARIO!O5="","",INVENTARIO!O5) | F5: =IF(INVENTARIO!Q5="","",INVENTARIO!Q5) | G5: =IF(OR(E5="",F5=""),"",E5-F5) | H5: =IF(INVENTARIO!T5="","",INVENTARIO!T5) | I5: =IF(INVENTARIO!U5="","",INVENTARIO!U5) | J5: =IF(INVENTARIO!V5="","",INVENTARIO!V5) | K5: =IF(INVENTARIO!R5="","",INVENTARIO!R5) | L5: =IF(INVENTARIO!Y5="","",INVENTARIO!Y5)
A6: =IF(INVENTARIO!A6="","",INVENTARIO!A6) -> EST-005 | B6: =IF(INVENTARIO!G6="","",INVENTARIO!G6) | C6: =IF(INVENTARIO!B6="","",INVENTARIO!B6) -> Dormitorio 2 | D6: =IF(INVENTARIO!D6="","",INVENTARIO!D6) -> Velador artesanal | E6: =IF(INVENTARIO!O6="","",INVENTARIO!O6) | F6: =IF(INVENTARIO!Q6="","",INVENTARIO!Q6) | G6: =IF(OR(E6="",F6=""),"",E6-F6) | H6: =IF(INVENTARIO!T6="","",INVENTARIO!T6) | I6: =IF(INVENTARIO!U6="","",INVENTARIO!U6) | J6: =IF(INVENTARIO!V6="","",INVENTARIO!V6) | K6: =IF(INVENTARIO!R6="","",INVENTARIO!R6) | L6: =IF(INVENTARIO!Y6="","",INVENTARIO!Y6)
A7: =IF(INVENTARIO!A7="","",INVENTARIO!A7) -> EST-006 | B7: =IF(INVENTARIO!G7="","",INVENTARIO!G7) | C7: =IF(INVENTARIO!B7="","",INVENTARIO!B7) -> Dormitorio 2 | D7: =IF(INVENTARIO!D7="","",INVENTARIO!D7) -> Cuadro caballo blanco | E7: =IF(INVENTARIO!O7="","",INVENTARIO!O7) | F7: =IF(INVENTARIO!Q7="","",INVENTARIO!Q7) | G7: =IF(OR(E7="",F7=""),"",E7-F7) | H7: =IF(INVENTARIO!T7="","",INVENTARIO!T7) | I7: =IF(INVENTARIO!U7="","",INVENTARIO!U7) | J7: =IF(INVENTARIO!V7="","",INVENTARIO!V7) | K7: =IF(INVENTARIO!R7="","",INVENTARIO!R7) | L7: =IF(INVENTARIO!Y7="","",INVENTARIO!Y7)
A8: =IF(INVENTARIO!A8="","",INVENTARIO!A8) -> EST-007 | B8: =IF(INVENTARIO!G8="","",INVENTARIO!G8) | C8: =IF(INVENTARIO!B8="","",INVENTARIO!B8) -> Dormitorio 2 | D8: =IF(INVENTARIO!D8="","",INVENTARIO!D8) -> Cuna + Cambiador + Cajonera | E8: =IF(INVENTARIO!O8="","",INVENTARIO!O8) | F8: =IF(INVENTARIO!Q8="","",INVENTARIO!Q8) | G8: =IF(OR(E8="",F8=""),"",E8-F8) | H8: =IF(INVENTARIO!T8="","",INVENTARIO!T8) | I8: =IF(INVENTARIO!U8="","",INVENTARIO!U8) | J8: =IF(INVENTARIO!V8="","",INVENTARIO!V8) | K8: =IF(INVENTARIO!R8="","",INVENTARIO!R8) | L8: =IF(INVENTARIO!Y8="","",INVENTARIO!Y8)
A9: =IF(INVENTARIO!A9="","",INVENTARIO!A9) -> EST-008 | B9: =IF(INVENTARIO!G9="","",INVENTARIO!G9) | C9: =IF(INVENTARIO!B9="","",INVENTARIO!B9) -> Dormitorio 2 | D9: =IF(INVENTARIO!D9="","",INVENTARIO!D9) -> Escritorio | E9: =IF(INVENTARIO!O9="","",INVENTARIO!O9) | F9: =IF(INVENTARIO!Q9="","",INVENTARIO!Q9) | G9: =IF(OR(E9="",F9=""),"",E9-F9) | H9: =IF(INVENTARIO!T9="","",INVENTARIO!T9) | I9: =IF(INVENTARIO!U9="","",INVENTARIO!U9) | J9: =IF(INVENTARIO!V9="","",INVENTARIO!V9) | K9: =IF(INVENTARIO!R9="","",INVENTARIO!R9) | L9: =IF(INVENTARIO!Y9="","",INVENTARIO!Y9)
A10: =IF(INVENTARIO!A10="","",INVENTARIO!A10) -> EST-009 | B10: =IF(INVENTARIO!G10="","",INVENTARIO!G10) | C10: =IF(INVENTARIO!B10="","",INVENTARIO!B10) -> Dormitorio 2 | D10: =IF(INVENTARIO!D10="","",INVENTARIO!D10) -> Sillon Matero de un cuerpo | E10: =IF(INVENTARIO!O10="","",INVENTARIO!O10) | F10: =IF(INVENTARIO!Q10="","",INVENTARIO!Q10) | G10: =IF(OR(E10="",F10=""),"",E10-F10) | H10: =IF(INVENTARIO!T10="","",INVENTARIO!T10) | I10: =IF(INVENTARIO!U10="","",INVENTARIO!U10) | J10: =IF(INVENTARIO!V10="","",INVENTARIO!V10) | K10: =IF(INVENTARIO!R10="","",INVENTARIO!R10) | L10: =IF(INVENTARIO!Y10="","",INVENTARIO!Y10)
A11: =IF(INVENTARIO!A11="","",INVENTARIO!A11) -> EST-010 | B11: =IF(INVENTARIO!G11="","",INVENTARIO!G11) -> 32' | C11: =IF(INVENTARIO!B11="","",INVENTARIO!B11) -> Dormitorio 2 | D11: =IF(INVENTARIO!D11="","",INVENTARIO!D11) -> TV Admiral 32' | E11: =IF(INVENTARIO!O11="","",INVENTARIO!O11) | F11: =IF(INVENTARIO!Q11="","",INVENTARIO!Q11) | G11: =IF(OR(E11="",F11=""),"",E11-F11) | H11: =IF(INVENTARIO!T11="","",INVENTARIO!T11) | I11: =IF(INVENTARIO!U11="","",INVENTARIO!U11) | J11: =IF(INVENTARIO!V11="","",INVENTARIO!V11) | K11: =IF(INVENTARIO!R11="","",INVENTARIO!R11) | L11: =IF(INVENTARIO!Y11="","",INVENTARIO!Y11)
A12: =IF(INVENTARIO!A12="","",INVENTARIO!A12) -> EST-011 | B12: =IF(INVENTARIO!G12="","",INVENTARIO!G12) | C12: =IF(INVENTARIO!B12="","",INVENTARIO!B12) -> Dormitorio 2 | D12: =IF(INVENTARIO!D12="","",INVENTARIO!D12) -> Estufa electrica ATMA | E12: =IF(INVENTARIO!O12="","",INVENTARIO!O12) | F12: =IF(INVENTARIO!Q12="","",INVENTARIO!Q12) | G12: =IF(OR(E12="",F12=""),"",E12-F12) | H12: =IF(INVENTARIO!T12="","",INVENTARIO!T12) | I12: =IF(INVENTARIO!U12="","",INVENTARIO!U12) | J12: =IF(INVENTARIO!V12="","",INVENTARIO!V12) | K12: =IF(INVENTARIO!R12="","",INVENTARIO!R12) | L12: =IF(INVENTARIO!Y12="","",INVENTARIO!Y12)
A13: =IF(INVENTARIO!A13="","",INVENTARIO!A13) -> EST-012 | B13: =IF(INVENTARIO!G13="","",INVENTARIO!G13) -> 43x31x65 | C13: =IF(INVENTARIO!B13="","",INVENTARIO!B13) -> Dormitorio 3 | D13: =IF(INVENTARIO!D13="","",INVENTARIO!D13) -> Mesa de luz blanca | E13: =IF(INVENTARIO!O13="","",INVENTARIO!O13) | F13: =IF(INVENTARIO!Q13="","",INVENTARIO!Q13) | G13: =IF(OR(E13="",F13=""),"",E13-F13) | H13: =IF(INVENTARIO!T13="","",INVENTARIO!T13) | I13: =IF(INVENTARIO!U13="","",INVENTARIO!U13) | J13: =IF(INVENTARIO!V13="","",INVENTARIO!V13) | K13: =IF(INVENTARIO!R13="","",INVENTARIO!R13) | L13: =IF(INVENTARIO!Y13="","",INVENTARIO!Y13)
... A77: =IF(INVENTARIO!A77="","",INVENTARIO!A77) -> EST-076 | B77: =IF(INVENTARIO!G77="","",INVENTARIO!G77) -> 200x100x50 | C77: =IF(INVENTARIO!B77="","",INVENTARIO!B77) -> Salon de juegos | D77: =IF(INVENTARIO!D77="","",INVENTARIO!D77) -> Mueble rustico | E77: =IF(INVENTARIO!O77="","",INVENTARIO!O77) | F77: =IF(INVENTARIO!Q77="","",INVENTARIO!Q77) | G77: =IF(OR(E77="",F77=""),"",E77-F77) | H77: =IF(INVENTARIO!T77="","",INVENTARIO!T77) | I77: =IF(INVENTARIO!U77="","",INVENTARIO!U77) | J77: =IF(INVENTARIO!V77="","",INVENTARIO!V77) | K77: =IF(INVENTARIO!R77="","",INVENTARIO!R77) | L77: =IF(INVENTARIO!Y77="","",INVENTARIO!Y77)
A78: =IF(#REF!="","",#REF!) -> #REF! | B78: =IF(#REF!="","",#REF!) -> #REF! | C78: =IF(#REF!="","",#REF!) -> #REF! | D78: =IF(#REF!="","",#REF!) -> #REF! | E78: =IF(INVENTARIO!O78="","",INVENTARIO!O78) | F78: =IF(INVENTARIO!Q78="","",INVENTARIO!Q78) | G78: =IF(OR(E78="",F78=""),"",E78-F78) | H78: =IF(INVENTARIO!T78="","",INVENTARIO!T78) | I78: =IF(INVENTARIO!U78="","",INVENTARIO!U78) | J78: =IF(INVENTARIO!V78="","",INVENTARIO!V78) | K78: =IF(INVENTARIO!R78="","",INVENTARIO!R78) | L78: =IF(INVENTARIO!Y78="","",INVENTARIO!Y78)
A79: =IF(INVENTARIO!A78="","",INVENTARIO!A78) -> EST-078 | B79: =IF(INVENTARIO!G78="","",INVENTARIO!G78) -> 1.90x70 | C79: =IF(INVENTARIO!B78="","",INVENTARIO!B78) -> Resibidor | D79: =IF(INVENTARIO!D78="","",INVENTARIO!D78) -> Sillon 3 cuerpos floreado | E79: =IF(INVENTARIO!O79="","",INVENTARIO!O79) | F79: =IF(INVENTARIO!Q79="","",INVENTARIO!Q79) | G79: =IF(OR(E79="",F79=""),"",E79-F79) | H79: =IF(INVENTARIO!T79="","",INVENTARIO!T79) | I79: =IF(INVENTARIO!U79="","",INVENTARIO!U79) | J79: =IF(INVENTARIO!V79="","",INVENTARIO!V79) | K79: =IF(INVENTARIO!R79="","",INVENTARIO!R79) | L79: =IF(INVENTARIO!Y79="","",INVENTARIO!Y79)
A80: =IF(INVENTARIO!A79="","",INVENTARIO!A79) -> EST-079 | B80: =IF(INVENTARIO!G79="","",INVENTARIO!G79) -> 1 M | C80: =IF(INVENTARIO!B79="","",INVENTARIO!B79) -> Resibidor | D80: =IF(INVENTARIO!D79="","",INVENTARIO!D79) -> Perchero de madera largo | E80: =IF(INVENTARIO!O80="","",INVENTARIO!O80) | F80: =IF(INVENTARIO!Q80="","",INVENTARIO!Q80) | G80: =IF(OR(E80="",F80=""),"",E80-F80) | H80: =IF(INVENTARIO!T80="","",INVENTARIO!T80) | I80: =IF(INVENTARIO!U80="","",INVENTARIO!U80) | J80: =IF(INVENTARIO!V80="","",INVENTARIO!V80) | K80: =IF(INVENTARIO!R80="","",INVENTARIO!R80) | L80: =IF(INVENTARIO!Y80="","",INVENTARIO!Y80)
A81: =IF(INVENTARIO!A80="","",INVENTARIO!A80) -> EST-080 | B81: =IF(INVENTARIO!G80="","",INVENTARIO!G80) | C81: =IF(INVENTARIO!B80="","",INVENTARIO!B80) -> Resibidor | D81: =IF(INVENTARIO!D80="","",INVENTARIO!D80) -> Cuadro caballo | E81: =IF(INVENTARIO!O81="","",INVENTARIO!O81) | F81: =IF(INVENTARIO!Q81="","",INVENTARIO!Q81) | G81: =IF(OR(E81="",F81=""),"",E81-F81) | H81: =IF(INVENTARIO!T81="","",INVENTARIO!T81) | I81: =IF(INVENTARIO!U81="","",INVENTARIO!U81) | J81: =IF(INVENTARIO!V81="","",INVENTARIO!V81) | K81: =IF(INVENTARIO!R81="","",INVENTARIO!R81) | L81: =IF(INVENTARIO!Y81="","",INVENTARIO!Y81)
A82: =IF(#REF!="","",#REF!) -> #REF! | B82: =IF(#REF!="","",#REF!) -> #REF! | C82: =IF(#REF!="","",#REF!) -> #REF! | D82: =IF(#REF!="","",#REF!) -> #REF! | E82: =IF(#REF!="","",#REF!) -> #REF! | F82: =IF(#REF!="","",#REF!) -> #REF! | G82: =IF(OR(E82="",F82=""),"",E82-F82) -> #REF! | H82: =IF(#REF!="","",#REF!) -> #REF! | I82: =IF(#REF!="","",#REF!) -> #REF! | J82: =IF(#REF!="","",#REF!) -> #REF! | K82: =IF(#REF!="","",#REF!) -> #REF! | L82: =IF(#REF!="","",#REF!) -> #REF!
A83: =IF(#REF!="","",#REF!) -> #REF! | B83: =IF(#REF!="","",#REF!) -> #REF! | C83: =IF(#REF!="","",#REF!) -> #REF! | D83: =IF(#REF!="","",#REF!) -> #REF! | E83: =IF(#REF!="","",#REF!) -> #REF! | F83: =IF(#REF!="","",#REF!) -> #REF! | G83: =IF(OR(E83="",F83=""),"",E83-F83) -> #REF! | H83: =IF(#REF!="","",#REF!) -> #REF! | I83: =IF(#REF!="","",#REF!) -> #REF! | J83: =IF(#REF!="","",#REF!) -> #REF! | K83: =IF(#REF!="","",#REF!) -> #REF! | L83: =IF(#REF!="","",#REF!) -> #REF!
A84: =IF(INVENTARIO!A81="","",INVENTARIO!A81) -> EST-083 | B84: =IF(INVENTARIO!G81="","",INVENTARIO!G81) -> 3x1.20 | C84: =IF(INVENTARIO!B81="","",INVENTARIO!B81) -> Comedor principal | D84: =IF(INVENTARIO!D81="","",INVENTARIO!D81) -> Mesa de madera grande 14 sillas | E84: =IF(INVENTARIO!O82="","",INVENTARIO!O82) | F84: =IF(INVENTARIO!Q82="","",INVENTARIO!Q82) | G84: =IF(OR(E84="",F84=""),"",E84-F84) | H84: =IF(INVENTARIO!T82="","",INVENTARIO!T82) | I84: =IF(INVENTARIO!U82="","",INVENTARIO!U82) | J84: =IF(INVENTARIO!V82="","",INVENTARIO!V82) | K84: =IF(INVENTARIO!R82="","",INVENTARIO!R82) | L84: =IF(INVENTARIO!Y82="","",INVENTARIO!Y82)
A85: =IF(INVENTARIO!A82="","",INVENTARIO!A82) -> EST-084 | B85: =IF(INVENTARIO!G82="","",INVENTARIO!G82) -> 2x1 | C85: =IF(INVENTARIO!B82="","",INVENTARIO!B82) -> Comedor principal | D85: =IF(INVENTARIO!D82="","",INVENTARIO!D82) -> Mesa de apoyo de madera | E85: =IF(INVENTARIO!O83="","",INVENTARIO!O83) | F85: =IF(INVENTARIO!Q83="","",INVENTARIO!Q83) | G85: =IF(OR(E85="",F85=""),"",E85-F85) | H85: =IF(INVENTARIO!T83="","",INVENTARIO!T83) | I85: =IF(INVENTARIO!U83="","",INVENTARIO!U83) | J85: =IF(INVENTARIO!V83="","",INVENTARIO!V83) | K85: =IF(INVENTARIO!R83="","",INVENTARIO!R83) | L85: =IF(INVENTARIO!Y83="","",INVENTARIO!Y83)
A86: =IF(INVENTARIO!A83="","",INVENTARIO!A83) -> EST-085 | B86: =IF(INVENTARIO!G83="","",INVENTARIO!G83) -> 1.5x2.3.65 | C86: =IF(INVENTARIO!B83="","",INVENTARIO!B83) -> Comedor principal | D86: =IF(INVENTARIO!D83="","",INVENTARIO!D83) -> Mueble de apoyo vintage | E86: =IF(INVENTARIO!O84="","",INVENTARIO!O84) | F86: =IF(INVENTARIO!Q84="","",INVENTARIO!Q84) | G86: =IF(OR(E86="",F86=""),"",E86-F86) | H86: =IF(INVENTARIO!T84="","",INVENTARIO!T84) | I86: =IF(INVENTARIO!U84="","",INVENTARIO!U84) | J86: =IF(INVENTARIO!V84="","",INVENTARIO!V84) | K86: =IF(INVENTARIO!R84="","",INVENTARIO!R84) | L86: =IF(INVENTARIO!Y84="","",INVENTARIO!Y84)
A87: =IF(#REF!="","",#REF!) -> #REF! | B87: =IF(#REF!="","",#REF!) -> #REF! | C87: =IF(#REF!="","",#REF!) -> #REF! | D87: =IF(#REF!="","",#REF!) -> #REF! | E87: =IF(#REF!="","",#REF!) -> #REF! | F87: =IF(#REF!="","",#REF!) -> #REF! | G87: =IF(OR(E87="",F87=""),"",E87-F87) -> #REF! | H87: =IF(#REF!="","",#REF!) -> #REF! | I87: =IF(#REF!="","",#REF!) -> #REF! | J87: =IF(#REF!="","",#REF!) -> #REF! | K87: =IF(#REF!="","",#REF!) -> #REF! | L87: =IF(#REF!="","",#REF!) -> #REF!
A88: =IF(#REF!="","",#REF!) -> #REF! | B88: =IF(#REF!="","",#REF!) -> #REF! | C88: =IF(#REF!="","",#REF!) -> #REF! | D88: =IF(#REF!="","",#REF!) -> #REF! | E88: =IF(#REF!="","",#REF!) -> #REF! | F88: =IF(#REF!="","",#REF!) -> #REF! | G88: =IF(OR(E88="",F88=""),"",E88-F88) -> #REF! | H88: =IF(#REF!="","",#REF!) -> #REF! | I88: =IF(#REF!="","",#REF!) -> #REF! | J88: =IF(#REF!="","",#REF!) -> #REF! | K88: =IF(#REF!="","",#REF!) -> #REF! | L88: =IF(#REF!="","",#REF!) -> #REF!
A89: =IF(INVENTARIO!A84="","",INVENTARIO!A84) -> EST-088 | B89: =IF(INVENTARIO!G84="","",INVENTARIO!G84) -> 1.20 | C89: =IF(INVENTARIO!B84="","",INVENTARIO!B84) -> Sector Bar | D89: =IF(INVENTARIO!D84="","",INVENTARIO!D84) -> Mesa redonda madera grande | E89: =IF(INVENTARIO!O85="","",INVENTARIO!O85) | F89: =IF(INVENTARIO!Q85="","",INVENTARIO!Q85) | G89: =IF(OR(E89="",F89=""),"",E89-F89) | H89: =IF(INVENTARIO!T85="","",INVENTARIO!T85) | I89: =IF(INVENTARIO!U85="","",INVENTARIO!U85) | J89: =IF(INVENTARIO!V85="","",INVENTARIO!V85) | K89: =IF(INVENTARIO!R85="","",INVENTARIO!R85) | L89: =IF(INVENTARIO!Y85="","",INVENTARIO!Y85)
A90: =IF(INVENTARIO!A85="","",INVENTARIO!A85) -> EST-089 | B90: =IF(INVENTARIO!G85="","",INVENTARIO!G85) | C90: =IF(INVENTARIO!B85="","",INVENTARIO!B85) -> Sector Bar | D90: =IF(INVENTARIO!D85="","",INVENTARIO!D85) -> Sillas X5 | E90: =IF(INVENTARIO!O86="","",INVENTARIO!O86) | F90: =IF(INVENTARIO!Q86="","",INVENTARIO!Q86) | G90: =IF(OR(E90="",F90=""),"",E90-F90) | H90: =IF(INVENTARIO!T86="","",INVENTARIO!T86) | I90: =IF(INVENTARIO!U86="","",INVENTARIO!U86) | J90: =IF(INVENTARIO!V86="","",INVENTARIO!V86) | K90: =IF(INVENTARIO!R86="","",INVENTARIO!R86) | L90: =IF(INVENTARIO!Y86="","",INVENTARIO!Y86)
A91: =IF(INVENTARIO!A86="","",INVENTARIO!A86) -> EST-090 | B91: =IF(INVENTARIO!G86="","",INVENTARIO!G86) | C91: =IF(INVENTARIO!B86="","",INVENTARIO!B86) -> Sector Bar | D91: =IF(INVENTARIO!D86="","",INVENTARIO!D86) -> Banquetas barra | E91: =IF(INVENTARIO!O87="","",INVENTARIO!O87) | F91: =IF(INVENTARIO!Q87="","",INVENTARIO!Q87) | G91: =IF(OR(E91="",F91=""),"",E91-F91) | H91: =IF(INVENTARIO!T87="","",INVENTARIO!T87) | I91: =IF(INVENTARIO!U87="","",INVENTARIO!U87) | J91: =IF(INVENTARIO!V87="","",INVENTARIO!V87) | K91: =IF(INVENTARIO!R87="","",INVENTARIO!R87) | L91: =IF(INVENTARIO!Y87="","",INVENTARIO!Y87)
A92: =IF(INVENTARIO!A87="","",INVENTARIO!A87) -> EST-091 | B92: =IF(INVENTARIO!G87="","",INVENTARIO!G87) | C92: =IF(INVENTARIO!B87="","",INVENTARIO!B87) -> Sector bar | D92: =IF(INVENTARIO!D87="","",INVENTARIO!D87) -> Tromen grande | E92: =IF(INVENTARIO!O88="","",INVENTARIO!O88) | F92: =IF(INVENTARIO!Q88="","",INVENTARIO!Q88) | G92: =IF(OR(E92="",F92=""),"",E92-F92) | H92: =IF(INVENTARIO!T88="","",INVENTARIO!T88) | I92: =IF(INVENTARIO!U88="","",INVENTARIO!U88) | J92: =IF(INVENTARIO!V88="","",INVENTARIO!V88) | K92: =IF(INVENTARIO!R88="","",INVENTARIO!R88) | L92: =IF(INVENTARIO!Y88="","",INVENTARIO!Y88)
A93: =IF(INVENTARIO!A88="","",INVENTARIO!A88) -> EST-092 | B93: =IF(INVENTARIO!G88="","",INVENTARIO!G88) | C93: =IF(INVENTARIO!B88="","",INVENTARIO!B88) | D93: =IF(INVENTARIO!D88="","",INVENTARIO!D88) | E93: =IF(INVENTARIO!O89="","",INVENTARIO!O89) | F93: =IF(INVENTARIO!Q89="","",INVENTARIO!Q89) | G93: =IF(OR(E93="",F93=""),"",E93-F93) | H93: =IF(INVENTARIO!T89="","",INVENTARIO!T89) | I93: =IF(INVENTARIO!U89="","",INVENTARIO!U89) | J93: =IF(INVENTARIO!V89="","",INVENTARIO!V89) | K93: =IF(INVENTARIO!R89="","",INVENTARIO!R89) | L93: =IF(INVENTARIO!Y89="","",INVENTARIO!Y89)
A94: =IF(INVENTARIO!A89="","",INVENTARIO!A89) -> EST-093 | B94: =IF(INVENTARIO!G89="","",INVENTARIO!G89) | C94: =IF(INVENTARIO!B89="","",INVENTARIO!B89) | D94: =IF(INVENTARIO!D89="","",INVENTARIO!D89) | E94: =IF(INVENTARIO!O90="","",INVENTARIO!O90) | F94: =IF(INVENTARIO!Q90="","",INVENTARIO!Q90) | G94: =IF(OR(E94="",F94=""),"",E94-F94) | H94: =IF(INVENTARIO!T90="","",INVENTARIO!T90) | I94: =IF(INVENTARIO!U90="","",INVENTARIO!U90) | J94: =IF(INVENTARIO!V90="","",INVENTARIO!V90) | K94: =IF(INVENTARIO!R90="","",INVENTARIO!R90) | L94: =IF(INVENTARIO!Y90="","",INVENTARIO!Y90)
A95: =IF(INVENTARIO!A90="","",INVENTARIO!A90) -> EST-094 | B95: =IF(INVENTARIO!G90="","",INVENTARIO!G90) -> 60x57x85 | C95: =IF(INVENTARIO!B90="","",INVENTARIO!B90) -> Lavadero | D95: =IF(INVENTARIO!D90="","",INVENTARIO!D90) -> Lavarropas LG | E95: =IF(INVENTARIO!O91="","",INVENTARIO!O91) | F95: =IF(INVENTARIO!Q91="","",INVENTARIO!Q91) | G95: =IF(OR(E95="",F95=""),"",E95-F95) | H95: =IF(INVENTARIO!T91="","",INVENTARIO!T91) | I95: =IF(INVENTARIO!U91="","",INVENTARIO!U91) | J95: =IF(INVENTARIO!V91="","",INVENTARIO!V91) | K95: =IF(INVENTARIO!R91="","",INVENTARIO!R91) | L95: =IF(INVENTARIO!Y91="","",INVENTARIO!Y91)
A96: =IF(INVENTARIO!A91="","",INVENTARIO!A91) -> EST-095 | B96: =IF(INVENTARIO!G91="","",INVENTARIO!G91) -> 60x55x85 | C96: =IF(INVENTARIO!B91="","",INVENTARIO!B91) -> Lavadero | D96: =IF(INVENTARIO!D91="","",INVENTARIO!D91) -> Lavarropas Drean | E96: =IF(INVENTARIO!O92="","",INVENTARIO!O92) | F96: =IF(INVENTARIO!Q92="","",INVENTARIO!Q92) | G96: =IF(OR(E96="",F96=""),"",E96-F96) | H96: =IF(INVENTARIO!T92="","",INVENTARIO!T92) | I96: =IF(INVENTARIO!U92="","",INVENTARIO!U92) | J96: =IF(INVENTARIO!V92="","",INVENTARIO!V92) | K96: =IF(INVENTARIO!R92="","",INVENTARIO!R92) | L96: =IF(INVENTARIO!Y92="","",INVENTARIO!Y92)
A97: =IF(INVENTARIO!A92="","",INVENTARIO!A92) -> EST-096 | B97: =IF(INVENTARIO!G92="","",INVENTARIO!G92) -> 60x55x85 | C97: =IF(INVENTARIO!B92="","",INVENTARIO!B92) -> Lavadero | D97: =IF(INVENTARIO!D92="","",INVENTARIO!D92) -> Lavarropas Drean | E97: =IF(INVENTARIO!O93="","",INVENTARIO!O93) | F97: =IF(INVENTARIO!Q93="","",INVENTARIO!Q93) | G97: =IF(OR(E97="",F97=""),"",E97-F97) | H97: =IF(INVENTARIO!T93="","",INVENTARIO!T93) | I97: =IF(INVENTARIO!U93="","",INVENTARIO!U93) | J97: =IF(INVENTARIO!V93="","",INVENTARIO!V93) | K97: =IF(INVENTARIO!R93="","",INVENTARIO!R93) | L97: =IF(INVENTARIO!Y93="","",INVENTARIO!Y93)
A98: =IF(INVENTARIO!A93="","",INVENTARIO!A93) -> EST-097 | B98: =IF(INVENTARIO!G93="","",INVENTARIO!G93) -> 60x55x85 | C98: =IF(INVENTARIO!B93="","",INVENTARIO!B93) -> Lavadero | D98: =IF(INVENTARIO!D93="","",INVENTARIO!D93) -> Lavarrolas Eslabon de Lujo | E98: =IF(INVENTARIO!O94="","",INVENTARIO!O94) | F98: =IF(INVENTARIO!Q94="","",INVENTARIO!Q94) | G98: =IF(OR(E98="",F98=""),"",E98-F98) | H98: =IF(INVENTARIO!T94="","",INVENTARIO!T94) | I98: =IF(INVENTARIO!U94="","",INVENTARIO!U94) | J98: =IF(INVENTARIO!V94="","",INVENTARIO!V94) | K98: =IF(INVENTARIO!R94="","",INVENTARIO!R94) | L98: =IF(INVENTARIO!Y94="","",INVENTARIO!Y94)
A99: =IF(INVENTARIO!A94="","",INVENTARIO!A94) -> EST-098 | B99: =IF(INVENTARIO!G94="","",INVENTARIO!G94) -> 60x55x85 | C99: =IF(INVENTARIO!B94="","",INVENTARIO!B94) -> Lavadero | D99: =IF(INVENTARIO!D94="","",INVENTARIO!D94) -> Secadora Philco | E99: =IF(INVENTARIO!O95="","",INVENTARIO!O95) | F99: =IF(INVENTARIO!Q95="","",INVENTARIO!Q95) | G99: =IF(OR(E99="",F99=""),"",E99-F99) | H99: =IF(INVENTARIO!T95="","",INVENTARIO!T95) | I99: =IF(INVENTARIO!U95="","",INVENTARIO!U95) | J99: =IF(INVENTARIO!V95="","",INVENTARIO!V95) | K99: =IF(INVENTARIO!R95="","",INVENTARIO!R95) | L99: =IF(INVENTARIO!Y95="","",INVENTARIO!Y95)
A100: =IF(INVENTARIO!A95="","",INVENTARIO!A95) -> EST-099 | B100: =IF(INVENTARIO!G95="","",INVENTARIO!G95) -> 1 Plaza | C100: =IF(INVENTARIO!B95="","",INVENTARIO!B95) -> Lavadero | D100: =IF(INVENTARIO!D95="","",INVENTARIO!D95) -> Sabanas blancas 1P | E100: =IF(INVENTARIO!O96="","",INVENTARIO!O96) | F100: =IF(INVENTARIO!Q96="","",INVENTARIO!Q96) | G100: =IF(OR(E100="",F100=""),"",E100-F100) | H100: =IF(INVENTARIO!T96="","",INVENTARIO!T96) | I100: =IF(INVENTARIO!U96="","",INVENTARIO!U96) | J100: =IF(INVENTARIO!V96="","",INVENTARIO!V96) | K100: =IF(INVENTARIO!R96="","",INVENTARIO!R96) | L100: =IF(INVENTARIO!Y96="","",INVENTARIO!Y96)
... A105: =IF(INVENTARIO!A100="","",INVENTARIO!A100) -> EST-104 | B105: =IF(INVENTARIO!G100="","",INVENTARIO!G100) | C105: =IF(INVENTARIO!B100="","",INVENTARIO!B100) -> Lavadero | D105: =IF(INVENTARIO!D100="","",INVENTARIO!D100) -> Repasadores | E105: =IF(INVENTARIO!O101="","",INVENTARIO!O101) | F105: =IF(INVENTARIO!Q101="","",INVENTARIO!Q101) | G105: =IF(OR(E105="",F105=""),"",E105-F105) | H105: =IF(INVENTARIO!T101="","",INVENTARIO!T101) | I105: =IF(INVENTARIO!U101="","",INVENTARIO!U101) | J105: =IF(INVENTARIO!V101="","",INVENTARIO!V101) | K105: =IF(INVENTARIO!R101="","",INVENTARIO!R101) | L105: =IF(INVENTARIO!Y101="","",INVENTARIO!Y101)
A106: =IF(INVENTARIO!A101="","",INVENTARIO!A101) -> EST-105 | B106: =IF(INVENTARIO!G101="","",INVENTARIO!G101) | C106: =IF(INVENTARIO!B101="","",INVENTARIO!B101) -> Lavadero | D106: =IF(INVENTARIO!D101="","",INVENTARIO!D101) -> Alfombra ducha | E106: =IF(#REF!="","",#REF!) -> #REF! | F106: =IF(#REF!="","",#REF!) -> #REF! | G106: =IF(OR(E106="",F106=""),"",E106-F106) -> #REF! | H106: =IF(#REF!="","",#REF!) -> #REF! | I106: =IF(#REF!="","",#REF!) -> #REF! | J106: =IF(#REF!="","",#REF!) -> #REF! | K106: =IF(#REF!="","",#REF!) -> #REF! | L106: =IF(#REF!="","",#REF!) -> #REF!
A107: =IF(#REF!="","",#REF!) -> #REF! | B107: =IF(#REF!="","",#REF!) -> #REF! | C107: =IF(#REF!="","",#REF!) -> #REF! | D107: =IF(#REF!="","",#REF!) -> #REF! | E107: =IF(#REF!="","",#REF!) -> #REF! | F107: =IF(#REF!="","",#REF!) -> #REF! | G107: =IF(OR(E107="",F107=""),"",E107-F107) -> #REF! | H107: =IF(#REF!="","",#REF!) -> #REF! | I107: =IF(#REF!="","",#REF!) -> #REF! | J107: =IF(#REF!="","",#REF!) -> #REF! | K107: =IF(#REF!="","",#REF!) -> #REF! | L107: =IF(#REF!="","",#REF!) -> #REF!
A108: =IF(#REF!="","",#REF!) -> #REF! | B108: =IF(#REF!="","",#REF!) -> #REF! | C108: =IF(#REF!="","",#REF!) -> #REF! | D108: =IF(#REF!="","",#REF!) -> #REF! | E108: =IF(INVENTARIO!O102="","",INVENTARIO!O102) | F108: =IF(INVENTARIO!Q102="","",INVENTARIO!Q102) | G108: =IF(OR(E108="",F108=""),"",E108-F108) | H108: =IF(INVENTARIO!T102="","",INVENTARIO!T102) | I108: =IF(INVENTARIO!U102="","",INVENTARIO!U102) | J108: =IF(INVENTARIO!V102="","",INVENTARIO!V102) | K108: =IF(INVENTARIO!R102="","",INVENTARIO!R102) | L108: =IF(INVENTARIO!Y102="","",INVENTARIO!Y102)
A109: =IF(INVENTARIO!A102="","",INVENTARIO!A102) -> EST-108 | B109: =IF(INVENTARIO!G102="","",INVENTARIO!G102) -> 2.5x1.50 | C109: =IF(INVENTARIO!B102="","",INVENTARIO!B102) -> Galería | D109: =IF(INVENTARIO!D102="","",INVENTARIO!D102) -> Mesa de hierro negra | E109: =IF(INVENTARIO!O103="","",INVENTARIO!O103) | F109: =IF(INVENTARIO!Q103="","",INVENTARIO!Q103) | G109: =IF(OR(E109="",F109=""),"",E109-F109) | H109: =IF(INVENTARIO!T103="","",INVENTARIO!T103) | I109: =IF(INVENTARIO!U103="","",INVENTARIO!U103) | J109: =IF(INVENTARIO!V103="","",INVENTARIO!V103) | K109: =IF(INVENTARIO!R103="","",INVENTARIO!R103) | L109: =IF(INVENTARIO!Y103="","",INVENTARIO!Y103)
A110: =IF(INVENTARIO!A103="","",INVENTARIO!A103) -> EST-109 | B110: =IF(INVENTARIO!G103="","",INVENTARIO!G103) | C110: =IF(INVENTARIO!B103="","",INVENTARIO!B103) -> Galería | D110: =IF(INVENTARIO!D103="","",INVENTARIO!D103) -> Mesa y silllas vintage con almohadones | E110: =IF(#REF!="","",#REF!) -> #REF! | F110: =IF(#REF!="","",#REF!) -> #REF! | G110: =IF(OR(E110="",F110=""),"",E110-F110) -> #REF! | H110: =IF(#REF!="","",#REF!) -> #REF! | I110: =IF(#REF!="","",#REF!) -> #REF! | J110: =IF(#REF!="","",#REF!) -> #REF! | K110: =IF(#REF!="","",#REF!) -> #REF! | L110: =IF(#REF!="","",#REF!) -> #REF!
A111: =IF(#REF!="","",#REF!) -> #REF! | B111: =IF(#REF!="","",#REF!) -> #REF! | C111: =IF(#REF!="","",#REF!) -> #REF! | D111: =IF(#REF!="","",#REF!) -> #REF! | E111: =IF(#REF!="","",#REF!) -> #REF! | F111: =IF(#REF!="","",#REF!) -> #REF! | G111: =IF(OR(E111="",F111=""),"",E111-F111) -> #REF! | H111: =IF(#REF!="","",#REF!) -> #REF! | I111: =IF(#REF!="","",#REF!) -> #REF! | J111: =IF(#REF!="","",#REF!) -> #REF! | K111: =IF(#REF!="","",#REF!) -> #REF! | L111: =IF(#REF!="","",#REF!) -> #REF!
A112: =IF(#REF!="","",#REF!) -> #REF! | B112: =IF(#REF!="","",#REF!) -> #REF! | C112: =IF(#REF!="","",#REF!) -> #REF! | D112: =IF(#REF!="","",#REF!) -> #REF! | E112: =IF(INVENTARIO!O104="","",INVENTARIO!O104) | F112: =IF(INVENTARIO!Q104="","",INVENTARIO!Q104) | G112: =IF(OR(E112="",F112=""),"",E112-F112) | H112: =IF(INVENTARIO!T104="","",INVENTARIO!T104) | I112: =IF(INVENTARIO!U104="","",INVENTARIO!U104) | J112: =IF(INVENTARIO!V104="","",INVENTARIO!V104) | K112: =IF(INVENTARIO!R104="","",INVENTARIO!R104) | L112: =IF(INVENTARIO!Y104="","",INVENTARIO!Y104)
A113: =IF(INVENTARIO!A104="","",INVENTARIO!A104) -> EST-112 | B113: =IF(INVENTARIO!G104="","",INVENTARIO!G104) | C113: =IF(INVENTARIO!B104="","",INVENTARIO!B104) -> Cocina | D113: =IF(INVENTARIO!D104="","",INVENTARIO!D104) -> Vasos de vidrio | E113: =IF(INVENTARIO!O105="","",INVENTARIO!O105) | F113: =IF(INVENTARIO!Q105="","",INVENTARIO!Q105) | G113: =IF(OR(E113="",F113=""),"",E113-F113) | H113: =IF(INVENTARIO!T105="","",INVENTARIO!T105) | I113: =IF(INVENTARIO!U105="","",INVENTARIO!U105) | J113: =IF(INVENTARIO!V105="","",INVENTARIO!V105) | K113: =IF(INVENTARIO!R105="","",INVENTARIO!R105) | L113: =IF(INVENTARIO!Y105="","",INVENTARIO!Y105)
A114: =IF(INVENTARIO!A105="","",INVENTARIO!A105) -> EST-113 | B114: =IF(INVENTARIO!G105="","",INVENTARIO!G105) | C114: =IF(INVENTARIO!B105="","",INVENTARIO!B105) -> Cocina | D114: =IF(INVENTARIO!D105="","",INVENTARIO!D105) -> Copas de agua | E114: =IF(INVENTARIO!O106="","",INVENTARIO!O106) | F114: =IF(INVENTARIO!Q106="","",INVENTARIO!Q106) | G114: =IF(OR(E114="",F114=""),"",E114-F114) | H114: =IF(INVENTARIO!T106="","",INVENTARIO!T106) | I114: =IF(INVENTARIO!U106="","",INVENTARIO!U106) | J114: =IF(INVENTARIO!V106="","",INVENTARIO!V106) | K114: =IF(INVENTARIO!R106="","",INVENTARIO!R106) | L114: =IF(INVENTARIO!Y106="","",INVENTARIO!Y106)
A115: =IF(INVENTARIO!A106="","",INVENTARIO!A106) -> EST-114 | B115: =IF(INVENTARIO!G106="","",INVENTARIO!G106) | C115: =IF(INVENTARIO!B106="","",INVENTARIO!B106) -> Cocina | D115: =IF(INVENTARIO!D106="","",INVENTARIO!D106) -> Jarras de vidrio | E115: =IF(INVENTARIO!O107="","",INVENTARIO!O107) | F115: =IF(INVENTARIO!Q107="","",INVENTARIO!Q107) | G115: =IF(OR(E115="",F115=""),"",E115-F115) | H115: =IF(INVENTARIO!T107="","",INVENTARIO!T107) | I115: =IF(INVENTARIO!U107="","",INVENTARIO!U107) | J115: =IF(INVENTARIO!V107="","",INVENTARIO!V107) | K115: =IF(INVENTARIO!R107="","",INVENTARIO!R107) | L115: =IF(INVENTARIO!Y107="","",INVENTARIO!Y107)
A116: =IF(INVENTARIO!A107="","",INVENTARIO!A107) -> EST-115 | B116: =IF(INVENTARIO!G107="","",INVENTARIO!G107) | C116: =IF(INVENTARIO!B107="","",INVENTARIO!B107) -> Cocina | D116: =IF(INVENTARIO!D107="","",INVENTARIO!D107) -> Jarras de plastico | E116: =IF(INVENTARIO!O108="","",INVENTARIO!O108) | F116: =IF(INVENTARIO!Q108="","",INVENTARIO!Q108) | G116: =IF(OR(E116="",F116=""),"",E116-F116) | H116: =IF(INVENTARIO!T108="","",INVENTARIO!T108) | I116: =IF(INVENTARIO!U108="","",INVENTARIO!U108) | J116: =IF(INVENTARIO!V108="","",INVENTARIO!V108) | K116: =IF(INVENTARIO!R108="","",INVENTARIO!R108) | L116: =IF(INVENTARIO!Y108="","",INVENTARIO!Y108)
A117: =IF(INVENTARIO!A108="","",INVENTARIO!A108) -> EST-116 | B117: =IF(INVENTARIO!G108="","",INVENTARIO!G108) | C117: =IF(INVENTARIO!B108="","",INVENTARIO!B108) -> Cocina | D117: =IF(INVENTARIO!D108="","",INVENTARIO!D108) -> vasos de plastico | E117: =IF(INVENTARIO!O109="","",INVENTARIO!O109) | F117: =IF(INVENTARIO!Q109="","",INVENTARIO!Q109) | G117: =IF(OR(E117="",F117=""),"",E117-F117) | H117: =IF(INVENTARIO!T109="","",INVENTARIO!T109) | I117: =IF(INVENTARIO!U109="","",INVENTARIO!U109) | J117: =IF(INVENTARIO!V109="","",INVENTARIO!V109) | K117: =IF(INVENTARIO!R109="","",INVENTARIO!R109) | L117: =IF(INVENTARIO!Y109="","",INVENTARIO!Y109)
A118: =IF(INVENTARIO!A109="","",INVENTARIO!A109) -> EST-117 | B118: =IF(INVENTARIO!G109="","",INVENTARIO!G109) | C118: =IF(INVENTARIO!B109="","",INVENTARIO!B109) -> Cocina | D118: =IF(INVENTARIO!D109="","",INVENTARIO!D109) -> Vajilla Platos | E118: =IF(INVENTARIO!O110="","",INVENTARIO!O110) | F118: =IF(INVENTARIO!Q110="","",INVENTARIO!Q110) | G118: =IF(OR(E118="",F118=""),"",E118-F118) | H118: =IF(INVENTARIO!T110="","",INVENTARIO!T110) | I118: =IF(INVENTARIO!U110="","",INVENTARIO!U110) | J118: =IF(INVENTARIO!V110="","",INVENTARIO!V110) | K118: =IF(INVENTARIO!R110="","",INVENTARIO!R110) | L118: =IF(INVENTARIO!Y110="","",INVENTARIO!Y110)
A119: =IF(INVENTARIO!A110="","",INVENTARIO!A110) -> EST-118 | B119: =IF(INVENTARIO!G110="","",INVENTARIO!G110) | C119: =IF(INVENTARIO!B110="","",INVENTARIO!B110) -> Cocina | D119: =IF(INVENTARIO!D110="","",INVENTARIO!D110) -> Fuentes de vidrio | E119: =IF(INVENTARIO!O111="","",INVENTARIO!O111) | F119: =IF(INVENTARIO!Q111="","",INVENTARIO!Q111) | G119: =IF(OR(E119="",F119=""),"",E119-F119) | H119: =IF(INVENTARIO!T111="","",INVENTARIO!T111) | I119: =IF(INVENTARIO!U111="","",INVENTARIO!U111) | J119: =IF(INVENTARIO!V111="","",INVENTARIO!V111) | K119: =IF(INVENTARIO!R111="","",INVENTARIO!R111) | L119: =IF(INVENTARIO!Y111="","",INVENTARIO!Y111)
A120: =IF(INVENTARIO!A111="","",INVENTARIO!A111) -> EST-119 | B120: =IF(INVENTARIO!G111="","",INVENTARIO!G111) | C120: =IF(INVENTARIO!B111="","",INVENTARIO!B111) -> Cocina | D120: =IF(INVENTARIO!D111="","",INVENTARIO!D111) -> Utencillos cocina | E120: =IF(INVENTARIO!O112="","",INVENTARIO!O112) | F120: =IF(INVENTARIO!Q112="","",INVENTARIO!Q112) | G120: =IF(OR(E120="",F120=""),"",E120-F120) | H120: =IF(INVENTARIO!T112="","",INVENTARIO!T112) | I120: =IF(INVENTARIO!U112="","",INVENTARIO!U112) | J120: =IF(INVENTARIO!V112="","",INVENTARIO!V112) | K120: =IF(INVENTARIO!R112="","",INVENTARIO!R112) | L120: =IF(INVENTARIO!Y112="","",INVENTARIO!Y112)
A121: =IF(INVENTARIO!A112="","",INVENTARIO!A112) -> EST-120 | B121: =IF(INVENTARIO!G112="","",INVENTARIO!G112) | C121: =IF(INVENTARIO!B112="","",INVENTARIO!B112) -> Cocina | D121: =IF(INVENTARIO!D112="","",INVENTARIO!D112) -> Tarteras y flanera | E121: =IF(INVENTARIO!O113="","",INVENTARIO!O113) | F121: =IF(INVENTARIO!Q113="","",INVENTARIO!Q113) | G121: =IF(OR(E121="",F121=""),"",E121-F121) | H121: =IF(INVENTARIO!T113="","",INVENTARIO!T113) | I121: =IF(INVENTARIO!U113="","",INVENTARIO!U113) | J121: =IF(INVENTARIO!V113="","",INVENTARIO!V113) | K121: =IF(INVENTARIO!R113="","",INVENTARIO!R113) | L121: =IF(INVENTARIO!Y113="","",INVENTARIO!Y113)
A122: =IF(INVENTARIO!A113="","",INVENTARIO!A113) -> EST-121 | B122: =IF(INVENTARIO!G113="","",INVENTARIO!G113) | C122: =IF(INVENTARIO!B113="","",INVENTARIO!B113) -> Cocina | D122: =IF(INVENTARIO!D113="","",INVENTARIO!D113) -> Cubiertos | E122: =IF(INVENTARIO!O114="","",INVENTARIO!O114) | F122: =IF(INVENTARIO!Q114="","",INVENTARIO!Q114) | G122: =IF(OR(E122="",F122=""),"",E122-F122) | H122: =IF(INVENTARIO!T114="","",INVENTARIO!T114) | I122: =IF(INVENTARIO!U114="","",INVENTARIO!U114) | J122: =IF(INVENTARIO!V114="","",INVENTARIO!V114) | K122: =IF(INVENTARIO!R114="","",INVENTARIO!R114) | L122: =IF(INVENTARIO!Y114="","",INVENTARIO!Y114)
A123: =IF(INVENTARIO!A114="","",INVENTARIO!A114) -> EST-122 | B123: =IF(INVENTARIO!G114="","",INVENTARIO!G114) | C123: =IF(INVENTARIO!B114="","",INVENTARIO!B114) -> Cocina | D123: =IF(INVENTARIO!D114="","",INVENTARIO!D114) -> Pizzera madera | E123: =IF(INVENTARIO!O115="","",INVENTARIO!O115) | F123: =IF(INVENTARIO!Q115="","",INVENTARIO!Q115) | G123: =IF(OR(E123="",F123=""),"",E123-F123) | H123: =IF(INVENTARIO!T115="","",INVENTARIO!T115) | I123: =IF(INVENTARIO!U115="","",INVENTARIO!U115) | J123: =IF(INVENTARIO!V115="","",INVENTARIO!V115) | K123: =IF(INVENTARIO!R115="","",INVENTARIO!R115) | L123: =IF(INVENTARIO!Y115="","",INVENTARIO!Y115)
A124: =IF(INVENTARIO!A115="","",INVENTARIO!A115) -> EST-123 | B124: =IF(INVENTARIO!G115="","",INVENTARIO!G115) | C124: =IF(INVENTARIO!B115="","",INVENTARIO!B115) -> Cocina | D124: =IF(INVENTARIO!D115="","",INVENTARIO!D115) -> 4 Fuentes de asado | E124: =IF(INVENTARIO!O116="","",INVENTARIO!O116) | F124: =IF(INVENTARIO!Q116="","",INVENTARIO!Q116) | G124: =IF(OR(E124="",F124=""),"",E124-F124) | H124: =IF(INVENTARIO!T116="","",INVENTARIO!T116) | I124: =IF(INVENTARIO!U116="","",INVENTARIO!U116) | J124: =IF(INVENTARIO!V116="","",INVENTARIO!V116) | K124: =IF(INVENTARIO!R116="","",INVENTARIO!R116) | L124: =IF(INVENTARIO!Y116="","",INVENTARIO!Y116)
... A501: =IF(INVENTARIO!A492="","",INVENTARIO!A492) | B501: =IF(INVENTARIO!G492="","",INVENTARIO!G492) | C501: =IF(INVENTARIO!B492="","",INVENTARIO!B492) | D501: =IF(INVENTARIO!D492="","",INVENTARIO!D492) | E501: =IF(INVENTARIO!O493="","",INVENTARIO!O493) | F501: =IF(INVENTARIO!Q493="","",INVENTARIO!Q493) | G501: =IF(OR(E501="",F501=""),"",E501-F501) | H501: =IF(INVENTARIO!T493="","",INVENTARIO!T493) | I501: =IF(INVENTARIO!U493="","",INVENTARIO!U493) | J501: =IF(INVENTARIO!V493="","",INVENTARIO!V493) | K501: =IF(INVENTARIO!R493="","",INVENTARIO!R493) | L501: =IF(INVENTARIO!Y493="","",INVENTARIO!Y493)

Sheet CATALOGO
A1: ID | B1: Artículo | C1: Ambiente | D1: Tipo | E1: Descripción | F1: Estado | G1: Nivel de valor | H1: Precio publicado | I1: Publicar | J1: Foto principal | K1: Fotos adicionales | L1: Observaciones
A2: =IF(INVENTARIO!A2="","",INVENTARIO!A2) -> EST-001 | B2: =IF(INVENTARIO!G2="","",INVENTARIO!G2) -> 2 Plazas | C2: =IF(INVENTARIO!B2="","",INVENTARIO!B2) -> Dormitorio 2 | D2: =IF(INVENTARIO!D2="","",INVENTARIO!D2) -> Sommier 2 Plazas | E2: =IF(INVENTARIO!H2="","",INVENTARIO!H2) | F2: =IF(INVENTARIO!L2="","",INVENTARIO!L2) -> EST-001.jpg | G2: =IF(#REF!="","",#REF!) -> #REF! | H2: =IF(INVENTARIO!O2="","",INVENTARIO!O2) | I2: =IF(INVENTARIO!S2="","",INVENTARIO!S2) | J2: =IF(INVENTARIO!W2="","",INVENTARIO!W2) | K2: =IF(INVENTARIO!X2="","",INVENTARIO!X2) | L2: =IF(INVENTARIO!Y2="","",INVENTARIO!Y2)
A3: =IF(INVENTARIO!A3="","",INVENTARIO!A3) -> EST-002 | B3: =IF(INVENTARIO!G3="","",INVENTARIO!G3) -> 2 Plazas | C3: =IF(INVENTARIO!B3="","",INVENTARIO!B3) -> Dormitorio 2 | D3: =IF(INVENTARIO!D3="","",INVENTARIO!D3) -> Respaldo negro | E3: =IF(INVENTARIO!H3="","",INVENTARIO!H3) -> Buen estado | F3: =IF(INVENTARIO!L3="","",INVENTARIO!L3) -> EST-002.jpg | G3: =IF(#REF!="","",#REF!) -> #REF! | H3: =IF(INVENTARIO!O3="","",INVENTARIO!O3) | I3: =IF(INVENTARIO!S3="","",INVENTARIO!S3) | J3: =IF(INVENTARIO!W3="","",INVENTARIO!W3) | K3: =IF(INVENTARIO!X3="","",INVENTARIO!X3) | L3: =IF(INVENTARIO!Y3="","",INVENTARIO!Y3)
A4: =IF(INVENTARIO!A4="","",INVENTARIO!A4) -> EST-003 | B4: =IF(INVENTARIO!G4="","",INVENTARIO!G4) -> 43x31x65 | C4: =IF(INVENTARIO!B4="","",INVENTARIO!B4) -> Dormitorio 2 | D4: =IF(INVENTARIO!D4="","",INVENTARIO!D4) -> Mesa de luz Blanca | E4: =IF(INVENTARIO!H4="","",INVENTARIO!H4) -> Buen estado | F4: =IF(INVENTARIO!L4="","",INVENTARIO!L4) -> EST-003.jpg | G4: =IF(#REF!="","",#REF!) -> #REF! | H4: =IF(INVENTARIO!O4="","",INVENTARIO!O4) | I4: =IF(INVENTARIO!S4="","",INVENTARIO!S4) | J4: =IF(INVENTARIO!W4="","",INVENTARIO!W4) | K4: =IF(INVENTARIO!X4="","",INVENTARIO!X4) | L4: =IF(INVENTARIO!Y4="","",INVENTARIO!Y4)
A5: =IF(INVENTARIO!A5="","",INVENTARIO!A5) -> EST-004 | B5: =IF(INVENTARIO!G5="","",INVENTARIO!G5) -> 43x31x65 | C5: =IF(INVENTARIO!B5="","",INVENTARIO!B5) -> Dormitorio 2 | D5: =IF(INVENTARIO!D5="","",INVENTARIO!D5) -> Mesa de luz Blanca | E5: =IF(INVENTARIO!H5="","",INVENTARIO!H5) -> Despintada | F5: =IF(INVENTARIO!L5="","",INVENTARIO!L5) -> EST-004.jpg | G5: =IF(#REF!="","",#REF!) -> #REF! | H5: =IF(INVENTARIO!O5="","",INVENTARIO!O5) | I5: =IF(INVENTARIO!S5="","",INVENTARIO!S5) | J5: =IF(INVENTARIO!W5="","",INVENTARIO!W5) | K5: =IF(INVENTARIO!X5="","",INVENTARIO!X5) | L5: =IF(INVENTARIO!Y5="","",INVENTARIO!Y5)
A6: =IF(INVENTARIO!A6="","",INVENTARIO!A6) -> EST-005 | B6: =IF(INVENTARIO!G6="","",INVENTARIO!G6) | C6: =IF(INVENTARIO!B6="","",INVENTARIO!B6) -> Dormitorio 2 | D6: =IF(INVENTARIO!D6="","",INVENTARIO!D6) -> Velador artesanal | E6: =IF(INVENTARIO!H6="","",INVENTARIO!H6) -> Buen estado | F6: =IF(INVENTARIO!L6="","",INVENTARIO!L6) -> EST-005.jpg | G6: =IF(#REF!="","",#REF!) -> #REF! | H6: =IF(INVENTARIO!O6="","",INVENTARIO!O6) | I6: =IF(INVENTARIO!S6="","",INVENTARIO!S6) | J6: =IF(INVENTARIO!W6="","",INVENTARIO!W6) | K6: =IF(INVENTARIO!X6="","",INVENTARIO!X6) | L6: =IF(INVENTARIO!Y6="","",INVENTARIO!Y6)
A7: =IF(INVENTARIO!A7="","",INVENTARIO!A7) -> EST-006 | B7: =IF(INVENTARIO!G7="","",INVENTARIO!G7) | C7: =IF(INVENTARIO!B7="","",INVENTARIO!B7) -> Dormitorio 2 | D7: =IF(INVENTARIO!D7="","",INVENTARIO!D7) -> Cuadro caballo blanco | E7: =IF(INVENTARIO!H7="","",INVENTARIO!H7) -> Buen estado | F7: =IF(INVENTARIO!L7="","",INVENTARIO!L7) -> EST-006.jpg | G7: =IF(#REF!="","",#REF!) -> #REF! | H7: =IF(INVENTARIO!O7="","",INVENTARIO!O7) | I7: =IF(INVENTARIO!S7="","",INVENTARIO!S7) | J7: =IF(INVENTARIO!W7="","",INVENTARIO!W7) | K7: =IF(INVENTARIO!X7="","",INVENTARIO!X7) | L7: =IF(INVENTARIO!Y7="","",INVENTARIO!Y7)
A8: =IF(INVENTARIO!A8="","",INVENTARIO!A8) -> EST-007 | B8: =IF(INVENTARIO!G8="","",INVENTARIO!G8) | C8: =IF(INVENTARIO!B8="","",INVENTARIO!B8) -> Dormitorio 2 | D8: =IF(INVENTARIO!D8="","",INVENTARIO!D8) -> Cuna + Cambiador + Cajonera | E8: =IF(INVENTARIO!H8="","",INVENTARIO!H8) -> Sin detalles | F8: =IF(INVENTARIO!L8="","",INVENTARIO!L8) -> EST-007.jpg | G8: =IF(#REF!="","",#REF!) -> #REF! | H8: =IF(INVENTARIO!O8="","",INVENTARIO!O8) | I8: =IF(INVENTARIO!S8="","",INVENTARIO!S8) | J8: =IF(INVENTARIO!W8="","",INVENTARIO!W8) | K8: =IF(INVENTARIO!X8="","",INVENTARIO!X8) | L8: =IF(INVENTARIO!Y8="","",INVENTARIO!Y8)
A9: =IF(INVENTARIO!A9="","",INVENTARIO!A9) -> EST-008 | B9: =IF(INVENTARIO!G9="","",INVENTARIO!G9) | C9: =IF(INVENTARIO!B9="","",INVENTARIO!B9) -> Dormitorio 2 | D9: =IF(INVENTARIO!D9="","",INVENTARIO!D9) -> Escritorio | E9: =IF(INVENTARIO!H9="","",INVENTARIO!H9) -> Buen estado | F9: =IF(INVENTARIO!L9="","",INVENTARIO!L9) -> EST-008.jpg | G9: =IF(#REF!="","",#REF!) -> #REF! | H9: =IF(INVENTARIO!O9="","",INVENTARIO!O9) | I9: =IF(INVENTARIO!S9="","",INVENTARIO!S9) | J9: =IF(INVENTARIO!W9="","",INVENTARIO!W9) | K9: =IF(INVENTARIO!X9="","",INVENTARIO!X9) | L9: =IF(INVENTARIO!Y9="","",INVENTARIO!Y9)
A10: =IF(INVENTARIO!A10="","",INVENTARIO!A10) -> EST-009 | B10: =IF(INVENTARIO!G10="","",INVENTARIO!G10) | C10: =IF(INVENTARIO!B10="","",INVENTARIO!B10) -> Dormitorio 2 | D10: =IF(INVENTARIO!D10="","",INVENTARIO!D10) -> Sillon Matero de un cuerpo | E10: =IF(INVENTARIO!H10="","",INVENTARIO!H10) -> Buen estado | F10: =IF(INVENTARIO!L10="","",INVENTARIO!L10) -> EST-009.jpg | G10: =IF(#REF!="","",#REF!) -> #REF! | H10: =IF(INVENTARIO!O10="","",INVENTARIO!O10) | I10: =IF(INVENTARIO!S10="","",INVENTARIO!S10) | J10: =IF(INVENTARIO!W10="","",INVENTARIO!W10) | K10: =IF(INVENTARIO!X10="","",INVENTARIO!X10) | L10: =IF(INVENTARIO!Y10="","",INVENTARIO!Y10)
A11: =IF(INVENTARIO!A11="","",INVENTARIO!A11) -> EST-010 | B11: =IF(INVENTARIO!G11="","",INVENTARIO!G11) -> 32' | C11: =IF(INVENTARIO!B11="","",INVENTARIO!B11) -> Dormitorio 2 | D11: =IF(INVENTARIO!D11="","",INVENTARIO!D11) -> TV Admiral 32' | E11: =IF(INVENTARIO!H11="","",INVENTARIO!H11) -> Buen estado | F11: =IF(INVENTARIO!L11="","",INVENTARIO!L11) -> EST-010.jpg | G11: =IF(#REF!="","",#REF!) -> #REF! | H11: =IF(INVENTARIO!O11="","",INVENTARIO!O11) | I11: =IF(INVENTARIO!S11="","",INVENTARIO!S11) | J11: =IF(INVENTARIO!W11="","",INVENTARIO!W11) | K11: =IF(INVENTARIO!X11="","",INVENTARIO!X11) | L11: =IF(INVENTARIO!Y11="","",INVENTARIO!Y11)
A12: =IF(INVENTARIO!A12="","",INVENTARIO!A12) -> EST-011 | B12: =IF(INVENTARIO!G12="","",INVENTARIO!G12) | C12: =IF(INVENTARIO!B12="","",INVENTARIO!B12) -> Dormitorio 2 | D12: =IF(INVENTARIO!D12="","",INVENTARIO!D12) -> Estufa electrica ATMA | E12: =IF(INVENTARIO!H12="","",INVENTARIO!H12) -> Buen estado | F12: =IF(INVENTARIO!L12="","",INVENTARIO!L12) -> EST-011.jpg | G12: =IF(#REF!="","",#REF!) -> #REF! | H12: =IF(INVENTARIO!O12="","",INVENTARIO!O12) | I12: =IF(INVENTARIO!S12="","",INVENTARIO!S12) | J12: =IF(INVENTARIO!W12="","",INVENTARIO!W12) | K12: =IF(INVENTARIO!X12="","",INVENTARIO!X12) | L12: =IF(INVENTARIO!Y12="","",INVENTARIO!Y12)
A13: =IF(INVENTARIO!A13="","",INVENTARIO!A13) -> EST-012 | B13: =IF(INVENTARIO!G13="","",INVENTARIO!G13) -> 43x31x65 | C13: =IF(INVENTARIO!B13="","",INVENTARIO!B13) -> Dormitorio 3 | D13: =IF(INVENTARIO!D13="","",INVENTARIO!D13) -> Mesa de luz blanca | E13: =IF(INVENTARIO!H13="","",INVENTARIO!H13) -> Buen estado | F13: =IF(INVENTARIO!L13="","",INVENTARIO!L13) -> EST-012.jpg | G13: =IF(#REF!="","",#REF!) -> #REF! | H13: =IF(INVENTARIO!O13="","",INVENTARIO!O13) | I13: =IF(INVENTARIO!S13="","",INVENTARIO!S13) | J13: =IF(INVENTARIO!W13="","",INVENTARIO!W13) | K13: =IF(INVENTARIO!X13="","",INVENTARIO!X13) | L13: =IF(INVENTARIO!Y13="","",INVENTARIO!Y13)
... A77: =IF(INVENTARIO!A77="","",INVENTARIO!A77) -> EST-076 | B77: =IF(INVENTARIO!G77="","",INVENTARIO!G77) -> 200x100x50 | C77: =IF(INVENTARIO!B77="","",INVENTARIO!B77) -> Salon de juegos | D77: =IF(INVENTARIO!D77="","",INVENTARIO!D77) -> Mueble rustico | E77: =IF(INVENTARIO!H77="","",INVENTARIO!H77) -> Buen estado | F77: =IF(INVENTARIO!L77="","",INVENTARIO!L77) | G77: =IF(#REF!="","",#REF!) -> #REF! | H77: =IF(INVENTARIO!O77="","",INVENTARIO!O77) | I77: =IF(INVENTARIO!S77="","",INVENTARIO!S77) | J77: =IF(INVENTARIO!W77="","",INVENTARIO!W77) | K77: =IF(INVENTARIO!X77="","",INVENTARIO!X77) | L77: =IF(INVENTARIO!Y77="","",INVENTARIO!Y77)
A78: =IF(#REF!="","",#REF!) -> #REF! | B78: =IF(#REF!="","",#REF!) -> #REF! | C78: =IF(#REF!="","",#REF!) -> #REF! | D78: =IF(#REF!="","",#REF!) -> #REF! | E78: =IF(#REF!="","",#REF!) -> #REF! | F78: =IF(#REF!="","",#REF!) -> #REF! | G78: =IF(#REF!="","",#REF!) -> #REF! | H78: =IF(INVENTARIO!O78="","",INVENTARIO!O78) | I78: =IF(INVENTARIO!S78="","",INVENTARIO!S78) | J78: =IF(INVENTARIO!W78="","",INVENTARIO!W78) | K78: =IF(INVENTARIO!X78="","",INVENTARIO!X78) | L78: =IF(INVENTARIO!Y78="","",INVENTARIO!Y78)
A79: =IF(INVENTARIO!A78="","",INVENTARIO!A78) -> EST-078 | B79: =IF(INVENTARIO!G78="","",INVENTARIO!G78) -> 1.90x70 | C79: =IF(INVENTARIO!B78="","",INVENTARIO!B78) -> Resibidor | D79: =IF(INVENTARIO!D78="","",INVENTARIO!D78) -> Sillon 3 cuerpos floreado | E79: =IF(INVENTARIO!H78="","",INVENTARIO!H78) -> Buen estado | F79: =IF(INVENTARIO!L78="","",INVENTARIO!L78) | G79: =IF(#REF!="","",#REF!) -> #REF! | H79: =IF(INVENTARIO!O79="","",INVENTARIO!O79) | I79: =IF(INVENTARIO!S79="","",INVENTARIO!S79) | J79: =IF(INVENTARIO!W79="","",INVENTARIO!W79) | K79: =IF(INVENTARIO!X79="","",INVENTARIO!X79) | L79: =IF(INVENTARIO!Y79="","",INVENTARIO!Y79)
A80: =IF(INVENTARIO!A79="","",INVENTARIO!A79) -> EST-079 | B80: =IF(INVENTARIO!G79="","",INVENTARIO!G79) -> 1 M | C80: =IF(INVENTARIO!B79="","",INVENTARIO!B79) -> Resibidor | D80: =IF(INVENTARIO!D79="","",INVENTARIO!D79) -> Perchero de madera largo | E80: =IF(INVENTARIO!H79="","",INVENTARIO!H79) -> Buen estado | F80: =IF(INVENTARIO!L79="","",INVENTARIO!L79) | G80: =IF(#REF!="","",#REF!) -> #REF! | H80: =IF(INVENTARIO!O80="","",INVENTARIO!O80) | I80: =IF(INVENTARIO!S80="","",INVENTARIO!S80) | J80: =IF(INVENTARIO!W80="","",INVENTARIO!W80) | K80: =IF(INVENTARIO!X80="","",INVENTARIO!X80) | L80: =IF(INVENTARIO!Y80="","",INVENTARIO!Y80)
A81: =IF(INVENTARIO!A80="","",INVENTARIO!A80) -> EST-080 | B81: =IF(INVENTARIO!G80="","",INVENTARIO!G80) | C81: =IF(INVENTARIO!B80="","",INVENTARIO!B80) -> Resibidor | D81: =IF(INVENTARIO!D80="","",INVENTARIO!D80) -> Cuadro caballo | E81: =IF(INVENTARIO!H80="","",INVENTARIO!H80) -> Buen estado | F81: =IF(INVENTARIO!L80="","",INVENTARIO!L80) | G81: =IF(#REF!="","",#REF!) -> #REF! | H81: =IF(INVENTARIO!O81="","",INVENTARIO!O81) | I81: =IF(INVENTARIO!S81="","",INVENTARIO!S81) | J81: =IF(INVENTARIO!W81="","",INVENTARIO!W81) | K81: =IF(INVENTARIO!X81="","",INVENTARIO!X81) | L81: =IF(INVENTARIO!Y81="","",INVENTARIO!Y81)
A82: =IF(#REF!="","",#REF!) -> #REF! | B82: =IF(#REF!="","",#REF!) -> #REF! | C82: =IF(#REF!="","",#REF!) -> #REF! | D82: =IF(#REF!="","",#REF!) -> #REF! | E82: =IF(#REF!="","",#REF!) -> #REF! | F82: =IF(#REF!="","",#REF!) -> #REF! | G82: =IF(#REF!="","",#REF!) -> #REF! | H82: =IF(#REF!="","",#REF!) -> #REF! | ... L82: =IF(#REF!="","",#REF!) -> #REF!
A83: =IF(#REF!="","",#REF!) -> #REF! | B83: =IF(#REF!="","",#REF!) -> #REF! | C83: =IF(#REF!="","",#REF!) -> #REF! | D83: =IF(#REF!="","",#REF!) -> #REF! | E83: =IF(#REF!="","",#REF!) -> #REF! | F83: =IF(#REF!="","",#REF!) -> #REF! | G83: =IF(#REF!="","",#REF!) -> #REF! | H83: =IF(#REF!="","",#REF!) -> #REF! | ... L83: =IF(#REF!="","",#REF!) -> #REF!
A84: =IF(INVENTARIO!A81="","",INVENTARIO!A81) -> EST-083 | B84: =IF(INVENTARIO!G81="","",INVENTARIO!G81) -> 3x1.20 | C84: =IF(INVENTARIO!B81="","",INVENTARIO!B81) -> Comedor principal | D84: =IF(INVENTARIO!D81="","",INVENTARIO!D81) -> Mesa de madera grande 14 sillas | E84: =IF(INVENTARIO!H81="","",INVENTARIO!H81) -> Buen estado | F84: =IF(INVENTARIO!L81="","",INVENTARIO!L81) | G84: =IF(#REF!="","",#REF!) -> #REF! | H84: =IF(INVENTARIO!O82="","",INVENTARIO!O82) | I84: =IF(INVENTARIO!S82="","",INVENTARIO!S82) | J84: =IF(INVENTARIO!W82="","",INVENTARIO!W82) | K84: =IF(INVENTARIO!X82="","",INVENTARIO!X82) | L84: =IF(INVENTARIO!Y82="","",INVENTARIO!Y82)
A85: =IF(INVENTARIO!A82="","",INVENTARIO!A82) -> EST-084 | B85: =IF(INVENTARIO!G82="","",INVENTARIO!G82) -> 2x1 | C85: =IF(INVENTARIO!B82="","",INVENTARIO!B82) -> Comedor principal | D85: =IF(INVENTARIO!D82="","",INVENTARIO!D82) -> Mesa de apoyo de madera | E85: =IF(INVENTARIO!H82="","",INVENTARIO!H82) -> Buen estado | F85: =IF(INVENTARIO!L82="","",INVENTARIO!L82) | G85: =IF(#REF!="","",#REF!) -> #REF! | H85: =IF(INVENTARIO!O83="","",INVENTARIO!O83) | I85: =IF(INVENTARIO!S83="","",INVENTARIO!S83) | J85: =IF(INVENTARIO!W83="","",INVENTARIO!W83) | K85: =IF(INVENTARIO!X83="","",INVENTARIO!X83) | L85: =IF(INVENTARIO!Y83="","",INVENTARIO!Y83)
A86: =IF(INVENTARIO!A83="","",INVENTARIO!A83) -> EST-085 | B86: =IF(INVENTARIO!G83="","",INVENTARIO!G83) -> 1.5x2.3.65 | C86: =IF(INVENTARIO!B83="","",INVENTARIO!B83) -> Comedor principal | D86: =IF(INVENTARIO!D83="","",INVENTARIO!D83) -> Mueble de apoyo vintage | E86: =IF(INVENTARIO!H83="","",INVENTARIO!H83) -> Buen estado | F86: =IF(INVENTARIO!L83="","",INVENTARIO!L83) | G86: =IF(#REF!="","",#REF!) -> #REF! | H86: =IF(INVENTARIO!O84="","",INVENTARIO!O84) | I86: =IF(INVENTARIO!S84="","",INVENTARIO!S84) | J86: =IF(INVENTARIO!W84="","",INVENTARIO!W84) | K86: =IF(INVENTARIO!X84="","",INVENTARIO!X84) | L86: =IF(INVENTARIO!Y84="","",INVENTARIO!Y84)
A87: =IF(#REF!="","",#REF!) -> #REF! | B87: =IF(#REF!="","",#REF!) -> #REF! | C87: =IF(#REF!="","",#REF!) -> #REF! | D87: =IF(#REF!="","",#REF!) -> #REF! | E87: =IF(#REF!="","",#REF!) -> #REF! | F87: =IF(#REF!="","",#REF!) -> #REF! | G87: =IF(#REF!="","",#REF!) -> #REF! | H87: =IF(#REF!="","",#REF!) -> #REF! | ... L87: =IF(#REF!="","",#REF!) -> #REF!
A88: =IF(#REF!="","",#REF!) -> #REF! | B88: =IF(#REF!="","",#REF!) -> #REF! | C88: =IF(#REF!="","",#REF!) -> #REF! | D88: =IF(#REF!="","",#REF!) -> #REF! | E88: =IF(#REF!="","",#REF!) -> #REF! | F88: =IF(#REF!="","",#REF!) -> #REF! | G88: =IF(#REF!="","",#REF!) -> #REF! | H88: =IF(#REF!="","",#REF!) -> #REF! | ... L88: =IF(#REF!="","",#REF!) -> #REF!
A89: =IF(INVENTARIO!A84="","",INVENTARIO!A84) -> EST-088 | B89: =IF(INVENTARIO!G84="","",INVENTARIO!G84) -> 1.20 | C89: =IF(INVENTARIO!B84="","",INVENTARIO!B84) -> Sector Bar | D89: =IF(INVENTARIO!D84="","",INVENTARIO!D84) -> Mesa redonda madera grande | E89: =IF(INVENTARIO!H84="","",INVENTARIO!H84) -> Buen estado | F89: =IF(INVENTARIO!L84="","",INVENTARIO!L84) | G89: =IF(#REF!="","",#REF!) -> #REF! | H89: =IF(INVENTARIO!O85="","",INVENTARIO!O85) | I89: =IF(INVENTARIO!S85="","",INVENTARIO!S85) | J89: =IF(INVENTARIO!W85="","",INVENTARIO!W85) | K89: =IF(INVENTARIO!X85="","",INVENTARIO!X85) | L89: =IF(INVENTARIO!Y85="","",INVENTARIO!Y85)
A90: =IF(INVENTARIO!A85="","",INVENTARIO!A85) -> EST-089 | B90: =IF(INVENTARIO!G85="","",INVENTARIO!G85) | C90: =IF(INVENTARIO!B85="","",INVENTARIO!B85) -> Sector Bar | D90: =IF(INVENTARIO!D85="","",INVENTARIO!D85) -> Sillas X5 | E90: =IF(INVENTARIO!H85="","",INVENTARIO!H85) -> Buen estado | F90: =IF(INVENTARIO!L85="","",INVENTARIO!L85) | G90: =IF(#REF!="","",#REF!) -> #REF! | H90: =IF(INVENTARIO!O86="","",INVENTARIO!O86) | I90: =IF(INVENTARIO!S86="","",INVENTARIO!S86) | J90: =IF(INVENTARIO!W86="","",INVENTARIO!W86) | K90: =IF(INVENTARIO!X86="","",INVENTARIO!X86) | L90: =IF(INVENTARIO!Y86="","",INVENTARIO!Y86)
A91: =IF(INVENTARIO!A86="","",INVENTARIO!A86) -> EST-090 | B91: =IF(INVENTARIO!G86="","",INVENTARIO!G86) | C91: =IF(INVENTARIO!B86="","",INVENTARIO!B86) -> Sector Bar | D91: =IF(INVENTARIO!D86="","",INVENTARIO!D86) -> Banquetas barra | E91: =IF(INVENTARIO!H86="","",INVENTARIO!H86) -> Buen estado | F91: =IF(INVENTARIO!L86="","",INVENTARIO!L86) | G91: =IF(#REF!="","",#REF!) -> #REF! | H91: =IF(INVENTARIO!O87="","",INVENTARIO!O87) | I91: =IF(INVENTARIO!S87="","",INVENTARIO!S87) | J91: =IF(INVENTARIO!W87="","",INVENTARIO!W87) | K91: =IF(INVENTARIO!X87="","",INVENTARIO!X87) | L91: =IF(INVENTARIO!Y87="","",INVENTARIO!Y87)
A92: =IF(INVENTARIO!A87="","",INVENTARIO!A87) -> EST-091 | B92: =IF(INVENTARIO!G87="","",INVENTARIO!G87) | C92: =IF(INVENTARIO!B87="","",INVENTARIO!B87) -> Sector bar | D92: =IF(INVENTARIO!D87="","",INVENTARIO!D87) -> Tromen grande | E92: =IF(INVENTARIO!H87="","",INVENTARIO!H87) -> Buen estado | F92: =IF(INVENTARIO!L87="","",INVENTARIO!L87) | G92: =IF(#REF!="","",#REF!) -> #REF! | H92: =IF(INVENTARIO!O88="","",INVENTARIO!O88) | I92: =IF(INVENTARIO!S88="","",INVENTARIO!S88) | J92: =IF(INVENTARIO!W88="","",INVENTARIO!W88) | K92: =IF(INVENTARIO!X88="","",INVENTARIO!X88) | L92: =IF(INVENTARIO!Y88="","",INVENTARIO!Y88)
A93: =IF(INVENTARIO!A88="","",INVENTARIO!A88) -> EST-092 | B93: =IF(INVENTARIO!G88="","",INVENTARIO!G88) | C93: =IF(INVENTARIO!B88="","",INVENTARIO!B88) | D93: =IF(INVENTARIO!D88="","",INVENTARIO!D88) | E93: =IF(INVENTARIO!H88="","",INVENTARIO!H88) | F93: =IF(INVENTARIO!L88="","",INVENTARIO!L88) | G93: =IF(#REF!="","",#REF!) -> #REF! | H93: =IF(INVENTARIO!O89="","",INVENTARIO!O89) | I93: =IF(INVENTARIO!S89="","",INVENTARIO!S89) | J93: =IF(INVENTARIO!W89="","",INVENTARIO!W89) | K93: =IF(INVENTARIO!X89="","",INVENTARIO!X89) | L93: =IF(INVENTARIO!Y89="","",INVENTARIO!Y89)
A94: =IF(INVENTARIO!A89="","",INVENTARIO!A89) -> EST-093 | B94: =IF(INVENTARIO!G89="","",INVENTARIO!G89) | C94: =IF(INVENTARIO!B89="","",INVENTARIO!B89) | D94: =IF(INVENTARIO!D89="","",INVENTARIO!D89) | E94: =IF(INVENTARIO!H89="","",INVENTARIO!H89) | F94: =IF(INVENTARIO!L89="","",INVENTARIO!L89) | G94: =IF(#REF!="","",#REF!) -> #REF! | H94: =IF(INVENTARIO!O90="","",INVENTARIO!O90) | I94: =IF(INVENTARIO!S90="","",INVENTARIO!S90) | J94: =IF(INVENTARIO!W90="","",INVENTARIO!W90) | K94: =IF(INVENTARIO!X90="","",INVENTARIO!X90) | L94: =IF(INVENTARIO!Y90="","",INVENTARIO!Y90)
A95: =IF(INVENTARIO!A90="","",INVENTARIO!A90) -> EST-094 | B95: =IF(INVENTARIO!G90="","",INVENTARIO!G90) -> 60x57x85 | C95: =IF(INVENTARIO!B90="","",INVENTARIO!B90) -> Lavadero | D95: =IF(INVENTARIO!D90="","",INVENTARIO!D90) -> Lavarropas LG | E95: =IF(INVENTARIO!H90="","",INVENTARIO!H90) -> Un poco oxidado funciona | F95: =IF(INVENTARIO!L90="","",INVENTARIO!L90) | G95: =IF(#REF!="","",#REF!) -> #REF! | H95: =IF(INVENTARIO!O91="","",INVENTARIO!O91) | I95: =IF(INVENTARIO!S91="","",INVENTARIO!S91) | J95: =IF(INVENTARIO!W91="","",INVENTARIO!W91) | K95: =IF(INVENTARIO!X91="","",INVENTARIO!X91) | L95: =IF(INVENTARIO!Y91="","",INVENTARIO!Y91)
A96: =IF(INVENTARIO!A91="","",INVENTARIO!A91) -> EST-095 | B96: =IF(INVENTARIO!G91="","",INVENTARIO!G91) -> 60x55x85 | C96: =IF(INVENTARIO!B91="","",INVENTARIO!B91) -> Lavadero | D96: =IF(INVENTARIO!D91="","",INVENTARIO!D91) -> Lavarropas Drean | E96: =IF(INVENTARIO!H91="","",INVENTARIO!H91) -> Buen estado | F96: =IF(INVENTARIO!L91="","",INVENTARIO!L91) | G96: =IF(#REF!="","",#REF!) -> #REF! | H96: =IF(INVENTARIO!O92="","",INVENTARIO!O92) | I96: =IF(INVENTARIO!S92="","",INVENTARIO!S92) | J96: =IF(INVENTARIO!W92="","",INVENTARIO!W92) | K96: =IF(INVENTARIO!X92="","",INVENTARIO!X92) | L96: =IF(INVENTARIO!Y92="","",INVENTARIO!Y92)
A97: =IF(INVENTARIO!A92="","",INVENTARIO!A92) -> EST-096 | B97: =IF(INVENTARIO!G92="","",INVENTARIO!G92) -> 60x55x85 | C97: =IF(INVENTARIO!B92="","",INVENTARIO!B92) -> Lavadero | D97: =IF(INVENTARIO!D92="","",INVENTARIO!D92) -> Lavarropas Drean | E97: =IF(INVENTARIO!H92="","",INVENTARIO!H92) -> Un poco oxidado funciona | F97: =IF(INVENTARIO!L92="","",INVENTARIO!L92) | G97: =IF(#REF!="","",#REF!) -> #REF! | H97: =IF(INVENTARIO!O93="","",INVENTARIO!O93) | I97: =IF(INVENTARIO!S93="","",INVENTARIO!S93) | J97: =IF(INVENTARIO!W93="","",INVENTARIO!W93) | K97: =IF(INVENTARIO!X93="","",INVENTARIO!X93) | L97: =IF(INVENTARIO!Y93="","",INVENTARIO!Y93)
A98: =IF(INVENTARIO!A93="","",INVENTARIO!A93) -> EST-097 | B98: =IF(INVENTARIO!G93="","",INVENTARIO!G93) -> 60x55x85 | C98: =IF(INVENTARIO!B93="","",INVENTARIO!B93) -> Lavadero | D98: =IF(INVENTARIO!D93="","",INVENTARIO!D93) -> Lavarrolas Eslabon de Lujo | E98: =IF(INVENTARIO!H93="","",INVENTARIO!H93) -> Buen estado | F98: =IF(INVENTARIO!L93="","",INVENTARIO!L93) | G98: =IF(#REF!="","",#REF!) -> #REF! | H98: =IF(INVENTARIO!O94="","",INVENTARIO!O94) | I98: =IF(INVENTARIO!S94="","",INVENTARIO!S94) | J98: =IF(INVENTARIO!W94="","",INVENTARIO!W94) | K98: =IF(INVENTARIO!X94="","",INVENTARIO!X94) | L98: =IF(INVENTARIO!Y94="","",INVENTARIO!Y94)
A99: =IF(INVENTARIO!A94="","",INVENTARIO!A94) -> EST-098 | B99: =IF(INVENTARIO!G94="","",INVENTARIO!G94) -> 60x55x85 | C99: =IF(INVENTARIO!B94="","",INVENTARIO!B94) -> Lavadero | D99: =IF(INVENTARIO!D94="","",INVENTARIO!D94) -> Secadora Philco | E99: =IF(INVENTARIO!H94="","",INVENTARIO!H94) -> Buen estado | F99: =IF(INVENTARIO!L94="","",INVENTARIO!L94) | G99: =IF(#REF!="","",#REF!) -> #REF! | H99: =IF(INVENTARIO!O95="","",INVENTARIO!O95) | I99: =IF(INVENTARIO!S95="","",INVENTARIO!S95) | J99: =IF(INVENTARIO!W95="","",INVENTARIO!W95) | K99: =IF(INVENTARIO!X95="","",INVENTARIO!X95) | L99: =IF(INVENTARIO!Y95="","",INVENTARIO!Y95)
A100: =IF(INVENTARIO!A95="","",INVENTARIO!A95) -> EST-099 | B100: =IF(INVENTARIO!G95="","",INVENTARIO!G95) -> 1 Plaza | C100: =IF(INVENTARIO!B95="","",INVENTARIO!B95) -> Lavadero | D100: =IF(INVENTARIO!D95="","",INVENTARIO!D95) -> Sabanas blancas 1P | E100: =IF(INVENTARIO!H95="","",INVENTARIO!H95) -> Buen estado | F100: =IF(INVENTARIO!L95="","",INVENTARIO!L95) | G100: =IF(#REF!="","",#REF!) -> #REF! | H100: =IF(INVENTARIO!O96="","",INVENTARIO!O96) | I100: =IF(INVENTARIO!S96="","",INVENTARIO!S96) | J100: =IF(INVENTARIO!W96="","",INVENTARIO!W96) | K100: =IF(INVENTARIO!X96="","",INVENTARIO!X96) | L100: =IF(INVENTARIO!Y96="","",INVENTARIO!Y96)
... A105: =IF(INVENTARIO!A100="","",INVENTARIO!A100) -> EST-104 | B105: =IF(INVENTARIO!G100="","",INVENTARIO!G100) | C105: =IF(INVENTARIO!B100="","",INVENTARIO!B100) -> Lavadero | D105: =IF(INVENTARIO!D100="","",INVENTARIO!D100) -> Repasadores | E105: =IF(INVENTARIO!H100="","",INVENTARIO!H100) -> Buen estado | F105: =IF(INVENTARIO!L100="","",INVENTARIO!L100) | G105: =IF(#REF!="","",#REF!) -> #REF! | H105: =IF(INVENTARIO!O101="","",INVENTARIO!O101) | I105: =IF(INVENTARIO!S101="","",INVENTARIO!S101) | J105: =IF(INVENTARIO!W101="","",INVENTARIO!W101) | K105: =IF(INVENTARIO!X101="","",INVENTARIO!X101) | L105: =IF(INVENTARIO!Y101="","",INVENTARIO!Y101)
A106: =IF(INVENTARIO!A101="","",INVENTARIO!A101) -> EST-105 | B106: =IF(INVENTARIO!G101="","",INVENTARIO!G101) | C106: =IF(INVENTARIO!B101="","",INVENTARIO!B101) -> Lavadero | D106: =IF(INVENTARIO!D101="","",INVENTARIO!D101) -> Alfombra ducha | E106: =IF(INVENTARIO!H101="","",INVENTARIO!H101) -> Buen estado | F106: =IF(INVENTARIO!L101="","",INVENTARIO!L101) | G106: =IF(#REF!="","",#REF!) -> #REF! | H106: =IF(#REF!="","",#REF!) -> #REF! | I106: =IF(#REF!="","",#REF!) -> #REF! | J106: =IF(#REF!="","",#REF!) -> #REF! | K106: =IF(#REF!="","",#REF!) -> #REF! | L106: =IF(#REF!="","",#REF!) -> #REF!
A107: =IF(#REF!="","",#REF!) -> #REF! | B107: =IF(#REF!="","",#REF!) -> #REF! | C107: =IF(#REF!="","",#REF!) -> #REF! | D107: =IF(#REF!="","",#REF!) -> #REF! | E107: =IF(#REF!="","",#REF!) -> #REF! | F107: =IF(#REF!="","",#REF!) -> #REF! | G107: =IF(#REF!="","",#REF!) -> #REF! | H107: =IF(#REF!="","",#REF!) -> #REF! | ... L107: =IF(#REF!="","",#REF!) -> #REF!
A108: =IF(#REF!="","",#REF!) -> #REF! | B108: =IF(#REF!="","",#REF!) -> #REF! | C108: =IF(#REF!="","",#REF!) -> #REF! | D108: =IF(#REF!="","",#REF!) -> #REF! | E108: =IF(#REF!="","",#REF!) -> #REF! | F108: =IF(#REF!="","",#REF!) -> #REF! | G108: =IF(#REF!="","",#REF!) -> #REF! | H108: =IF(INVENTARIO!O102="","",INVENTARIO!O102) | I108: =IF(INVENTARIO!S102="","",INVENTARIO!S102) | J108: =IF(INVENTARIO!W102="","",INVENTARIO!W102) | K108: =IF(INVENTARIO!X102="","",INVENTARIO!X102) | L108: =IF(INVENTARIO!Y102="","",INVENTARIO!Y102)
A109: =IF(INVENTARIO!A102="","",INVENTARIO!A102) -> EST-108 | B109: =IF(INVENTARIO!G102="","",INVENTARIO!G102) -> 2.5x1.50 | C109: =IF(INVENTARIO!B102="","",INVENTARIO!B102) -> Galería | D109: =IF(INVENTARIO!D102="","",INVENTARIO!D102) -> Mesa de hierro negra | E109: =IF(INVENTARIO!H102="","",INVENTARIO!H102) -> Buen estado | F109: =IF(INVENTARIO!L102="","",INVENTARIO!L102) | G109: =IF(#REF!="","",#REF!) -> #REF! | H109: =IF(INVENTARIO!O103="","",INVENTARIO!O103) | I109: =IF(INVENTARIO!S103="","",INVENTARIO!S103) | J109: =IF(INVENTARIO!W103="","",INVENTARIO!W103) | K109: =IF(INVENTARIO!X103="","",INVENTARIO!X103) | L109: =IF(INVENTARIO!Y103="","",INVENTARIO!Y103)
A110: =IF(INVENTARIO!A103="","",INVENTARIO!A103) -> EST-109 | B110: =IF(INVENTARIO!G103="","",INVENTARIO!G103) | C110: =IF(INVENTARIO!B103="","",INVENTARIO!B103) -> Galería | D110: =IF(INVENTARIO!D103="","",INVENTARIO!D103) -> Mesa y silllas vintage con almohadones | E110: =IF(INVENTARIO!H103="","",INVENTARIO!H103) -> Buen estado | F110: =IF(INVENTARIO!L103="","",INVENTARIO!L103) | G110: =IF(#REF!="","",#REF!) -> #REF! | H110: =IF(#REF!="","",#REF!) -> #REF! | I110: =IF(#REF!="","",#REF!) -> #REF! | J110: =IF(#REF!="","",#REF!) -> #REF! | K110: =IF(#REF!="","",#REF!) -> #REF! | L110: =IF(#REF!="","",#REF!) -> #REF!
A111: =IF(#REF!="","",#REF!) -> #REF! | B111: =IF(#REF!="","",#REF!) -> #REF! | C111: =IF(#REF!="","",#REF!) -> #REF! | D111: =IF(#REF!="","",#REF!) -> #REF! | E111: =IF(#REF!="","",#REF!) -> #REF! | F111: =IF(#REF!="","",#REF!) -> #REF! | G111: =IF(#REF!="","",#REF!) -> #REF! | H111: =IF(#REF!="","",#REF!) -> #REF! | ... L111: =IF(#REF!="","",#REF!) -> #REF!
A112: =IF(#REF!="","",#REF!) -> #REF! | B112: =IF(#REF!="","",#REF!) -> #REF! | C112: =IF(#REF!="","",#REF!) -> #REF! | D112: =IF(#REF!="","",#REF!) -> #REF! | E112: =IF(#REF!="","",#REF!) -> #REF! | F112: =IF(#REF!="","",#REF!) -> #REF! | G112: =IF(#REF!="","",#REF!) -> #REF! | H112: =IF(INVENTARIO!O104="","",INVENTARIO!O104) | I112: =IF(INVENTARIO!S104="","",INVENTARIO!S104) | J112: =IF(INVENTARIO!W104="","",INVENTARIO!W104) | K112: =IF(INVENTARIO!X104="","",INVENTARIO!X104) | L112: =IF(INVENTARIO!Y104="","",INVENTARIO!Y104)
A113: =IF(INVENTARIO!A104="","",INVENTARIO!A104) -> EST-112 | B113: =IF(INVENTARIO!G104="","",INVENTARIO!G104) | C113: =IF(INVENTARIO!B104="","",INVENTARIO!B104) -> Cocina | D113: =IF(INVENTARIO!D104="","",INVENTARIO!D104) -> Vasos de vidrio | E113: =IF(INVENTARIO!H104="","",INVENTARIO!H104) -> Buen estado | F113: =IF(INVENTARIO!L104="","",INVENTARIO!L104) | G113: =IF(#REF!="","",#REF!) -> #REF! | H113: =IF(INVENTARIO!O105="","",INVENTARIO!O105) | I113: =IF(INVENTARIO!S105="","",INVENTARIO!S105) | J113: =IF(INVENTARIO!W105="","",INVENTARIO!W105) | K113: =IF(INVENTARIO!X105="","",INVENTARIO!X105) | L113: =IF(INVENTARIO!Y105="","",INVENTARIO!Y105)
A114: =IF(INVENTARIO!A105="","",INVENTARIO!A105) -> EST-113 | B114: =IF(INVENTARIO!G105="","",INVENTARIO!G105) | C114: =IF(INVENTARIO!B105="","",INVENTARIO!B105) -> Cocina | D114: =IF(INVENTARIO!D105="","",INVENTARIO!D105) -> Copas de agua | E114: =IF(INVENTARIO!H105="","",INVENTARIO!H105) -> Buen estado | F114: =IF(INVENTARIO!L105="","",INVENTARIO!L105) | G114: =IF(#REF!="","",#REF!) -> #REF! | H114: =IF(INVENTARIO!O106="","",INVENTARIO!O106) | I114: =IF(INVENTARIO!S106="","",INVENTARIO!S106) | J114: =IF(INVENTARIO!W106="","",INVENTARIO!W106) | K114: =IF(INVENTARIO!X106="","",INVENTARIO!X106) | L114: =IF(INVENTARIO!Y106="","",INVENTARIO!Y106)
A115: =IF(INVENTARIO!A106="","",INVENTARIO!A106) -> EST-114 | B115: =IF(INVENTARIO!G106="","",INVENTARIO!G106) | C115: =IF(INVENTARIO!B106="","",INVENTARIO!B106) -> Cocina | D115: =IF(INVENTARIO!D106="","",INVENTARIO!D106) -> Jarras de vidrio | E115: =IF(INVENTARIO!H106="","",INVENTARIO!H106) -> Buen estado | F115: =IF(INVENTARIO!L106="","",INVENTARIO!L106) | G115: =IF(#REF!="","",#REF!) -> #REF! | H115: =IF(INVENTARIO!O107="","",INVENTARIO!O107) | I115: =IF(INVENTARIO!S107="","",INVENTARIO!S107) | J115: =IF(INVENTARIO!W107="","",INVENTARIO!W107) | K115: =IF(INVENTARIO!X107="","",INVENTARIO!X107) | L115: =IF(INVENTARIO!Y107="","",INVENTARIO!Y107)
A116: =IF(INVENTARIO!A107="","",INVENTARIO!A107) -> EST-115 | B116: =IF(INVENTARIO!G107="","",INVENTARIO!G107) | C116: =IF(INVENTARIO!B107="","",INVENTARIO!B107) -> Cocina | D116: =IF(INVENTARIO!D107="","",INVENTARIO!D107) -> Jarras de plastico | E116: =IF(INVENTARIO!H107="","",INVENTARIO!H107) -> Buen estado | F116: =IF(INVENTARIO!L107="","",INVENTARIO!L107) | G116: =IF(#REF!="","",#REF!) -> #REF! | H116: =IF(INVENTARIO!O108="","",INVENTARIO!O108) | I116: =IF(INVENTARIO!S108="","",INVENTARIO!S108) | J116: =IF(INVENTARIO!W108="","",INVENTARIO!W108) | K116: =IF(INVENTARIO!X108="","",INVENTARIO!X108) | L116: =IF(INVENTARIO!Y108="","",INVENTARIO!Y108)
A117: =IF(INVENTARIO!A108="","",INVENTARIO!A108) -> EST-116 | B117: =IF(INVENTARIO!G108="","",INVENTARIO!G108) | C117: =IF(INVENTARIO!B108="","",INVENTARIO!B108) -> Cocina | D117: =IF(INVENTARIO!D108="","",INVENTARIO!D108) -> vasos de plastico | E117: =IF(INVENTARIO!H108="","",INVENTARIO!H108) -> Buen estado | F117: =IF(INVENTARIO!L108="","",INVENTARIO!L108) | G117: =IF(#REF!="","",#REF!) -> #REF! | H117: =IF(INVENTARIO!O109="","",INVENTARIO!O109) | I117: =IF(INVENTARIO!S109="","",INVENTARIO!S109) | J117: =IF(INVENTARIO!W109="","",INVENTARIO!W109) | K117: =IF(INVENTARIO!X109="","",INVENTARIO!X109) | L117: =IF(INVENTARIO!Y109="","",INVENTARIO!Y109)
A118: =IF(INVENTARIO!A109="","",INVENTARIO!A109) -> EST-117 | B118: =IF(INVENTARIO!G109="","",INVENTARIO!G109) | C118: =IF(INVENTARIO!B109="","",INVENTARIO!B109) -> Cocina | D118: =IF(INVENTARIO!D109="","",INVENTARIO!D109) -> Vajilla Platos | E118: =IF(INVENTARIO!H109="","",INVENTARIO!H109) -> Buen estado | F118: =IF(INVENTARIO!L109="","",INVENTARIO!L109) | G118: =IF(#REF!="","",#REF!) -> #REF! | H118: =IF(INVENTARIO!O110="","",INVENTARIO!O110) | I118: =IF(INVENTARIO!S110="","",INVENTARIO!S110) | J118: =IF(INVENTARIO!W110="","",INVENTARIO!W110) | K118: =IF(INVENTARIO!X110="","",INVENTARIO!X110) | L118: =IF(INVENTARIO!Y110="","",INVENTARIO!Y110)
A119: =IF(INVENTARIO!A110="","",INVENTARIO!A110) -> EST-118 | B119: =IF(INVENTARIO!G110="","",INVENTARIO!G110) | C119: =IF(INVENTARIO!B110="","",INVENTARIO!B110) -> Cocina | D119: =IF(INVENTARIO!D110="","",INVENTARIO!D110) -> Fuentes de vidrio | E119: =IF(INVENTARIO!H110="","",INVENTARIO!H110) -> Buen estado | F119: =IF(INVENTARIO!L110="","",INVENTARIO!L110) | G119: =IF(#REF!="","",#REF!) -> #REF! | H119: =IF(INVENTARIO!O111="","",INVENTARIO!O111) | I119: =IF(INVENTARIO!S111="","",INVENTARIO!S111) | J119: =IF(INVENTARIO!W111="","",INVENTARIO!W111) | K119: =IF(INVENTARIO!X111="","",INVENTARIO!X111) | L119: =IF(INVENTARIO!Y111="","",INVENTARIO!Y111)
A120: =IF(INVENTARIO!A111="","",INVENTARIO!A111) -> EST-119 | B120: =IF(INVENTARIO!G111="","",INVENTARIO!G111) | C120: =IF(INVENTARIO!B111="","",INVENTARIO!B111) -> Cocina | D120: =IF(INVENTARIO!D111="","",INVENTARIO!D111) -> Utencillos cocina | E120: =IF(INVENTARIO!H111="","",INVENTARIO!H111) -> Buen estado | F120: =IF(INVENTARIO!L111="","",INVENTARIO!L111) | G120: =IF(#REF!="","",#REF!) -> #REF! | H120: =IF(INVENTARIO!O112="","",INVENTARIO!O112) | I120: =IF(INVENTARIO!S112="","",INVENTARIO!S112) | J120: =IF(INVENTARIO!W112="","",INVENTARIO!W112) | K120: =IF(INVENTARIO!X112="","",INVENTARIO!X112) | L120: =IF(INVENTARIO!Y112="","",INVENTARIO!Y112)
A121: =IF(INVENTARIO!A112="","",INVENTARIO!A112) -> EST-120 | B121: =IF(INVENTARIO!G112="","",INVENTARIO!G112) | C121: =IF(INVENTARIO!B112="","",INVENTARIO!B112) -> Cocina | D121: =IF(INVENTARIO!D112="","",INVENTARIO!D112) -> Tarteras y flanera | E121: =IF(INVENTARIO!H112="","",INVENTARIO!H112) -> Buen estado | F121: =IF(INVENTARIO!L112="","",INVENTARIO!L112) | G121: =IF(#REF!="","",#REF!) -> #REF! | H121: =IF(INVENTARIO!O113="","",INVENTARIO!O113) | I121: =IF(INVENTARIO!S113="","",INVENTARIO!S113) | J121: =IF(INVENTARIO!W113="","",INVENTARIO!W113) | K121: =IF(INVENTARIO!X113="","",INVENTARIO!X113) | L121: =IF(INVENTARIO!Y113="","",INVENTARIO!Y113)
A122: =IF(INVENTARIO!A113="","",INVENTARIO!A113) -> EST-121 | B122: =IF(INVENTARIO!G113="","",INVENTARIO!G113) | C122: =IF(INVENTARIO!B113="","",INVENTARIO!B113) -> Cocina | D122: =IF(INVENTARIO!D113="","",INVENTARIO!D113) -> Cubiertos | E122: =IF(INVENTARIO!H113="","",INVENTARIO!H113) -> Buen estado | F122: =IF(INVENTARIO!L113="","",INVENTARIO!L113) | G122: =IF(#REF!="","",#REF!) -> #REF! | H122: =IF(INVENTARIO!O114="","",INVENTARIO!O114) | I122: =IF(INVENTARIO!S114="","",INVENTARIO!S114) | J122: =IF(INVENTARIO!W114="","",INVENTARIO!W114) | K122: =IF(INVENTARIO!X114="","",INVENTARIO!X114) | L122: =IF(INVENTARIO!Y114="","",INVENTARIO!Y114)
A123: =IF(INVENTARIO!A114="","",INVENTARIO!A114) -> EST-122 | B123: =IF(INVENTARIO!G114="","",INVENTARIO!G114) | C123: =IF(INVENTARIO!B114="","",INVENTARIO!B114) -> Cocina | D123: =IF(INVENTARIO!D114="","",INVENTARIO!D114) -> Pizzera madera | E123: =IF(INVENTARIO!H114="","",INVENTARIO!H114) -> Buen estado | F123: =IF(INVENTARIO!L114="","",INVENTARIO!L114) | G123: =IF(#REF!="","",#REF!) -> #REF! | H123: =IF(INVENTARIO!O115="","",INVENTARIO!O115) | I123: =IF(INVENTARIO!S115="","",INVENTARIO!S115) | J123: =IF(INVENTARIO!W115="","",INVENTARIO!W115) | K123: =IF(INVENTARIO!X115="","",INVENTARIO!X115) | L123: =IF(INVENTARIO!Y115="","",INVENTARIO!Y115)
A124: =IF(INVENTARIO!A115="","",INVENTARIO!A115) -> EST-123 | B124: =IF(INVENTARIO!G115="","",INVENTARIO!G115) | C124: =IF(INVENTARIO!B115="","",INVENTARIO!B115) -> Cocina | D124: =IF(INVENTARIO!D115="","",INVENTARIO!D115) -> 4 Fuentes de asado | E124: =IF(INVENTARIO!H115="","",INVENTARIO!H115) -> Buen estado | F124: =IF(INVENTARIO!L115="","",INVENTARIO!L115) | G124: =IF(#REF!="","",#REF!) -> #REF! | H124: =IF(INVENTARIO!O116="","",INVENTARIO!O116) | I124: =IF(INVENTARIO!S116="","",INVENTARIO!S116) | J124: =IF(INVENTARIO!W116="","",INVENTARIO!W116) | K124: =IF(INVENTARIO!X116="","",INVENTARIO!X116) | L124: =IF(INVENTARIO!Y116="","",INVENTARIO!Y116)
... A501: =IF(INVENTARIO!A492="","",INVENTARIO!A492) | B501: =IF(INVENTARIO!G492="","",INVENTARIO!G492) | C501: =IF(INVENTARIO!B492="","",INVENTARIO!B492) | D501: =IF(INVENTARIO!D492="","",INVENTARIO!D492) | E501: =IF(INVENTARIO!H492="","",INVENTARIO!H492) | F501: =IF(INVENTARIO!L492="","",INVENTARIO!L492) | G501: =IF(#REF!="","",#REF!) -> #REF! | H501: =IF(INVENTARIO!O493="","",INVENTARIO!O493) | I501: =IF(INVENTARIO!S493="","",INVENTARIO!S493) | J501: =IF(INVENTARIO!W493="","",INVENTARIO!W493) | K501: =IF(INVENTARIO!X493="","",INVENTARIO!X493) | L501: =IF(INVENTARIO!Y493="","",INVENTARIO!Y493)

Sheet AMBIENTES
A1: ID | B1: Ambiente / Sector | C1: Zona | D1: Prioridad de relevamiento | E1: Observaciones
A2: AMB-01 | B2: Casco / Casa principal | C2: Interior | D2: Normal
A3: AMB-02 | B3: Living principal | C3: Interior | D3: Alta
A4: AMB-03 | B4: Living secundario | C4: Interior | D4: Normal
A5: AMB-04 | B5: Comedor principal | C5: Interior | D5: Alta
A6: AMB-05 | B6: Comedor secundario | C6: Interior | D6: Normal
A7: AMB-06 | B7: Cocina | C7: Interior | D7: Alta
A8: AMB-07 | B8: Dormitorio principal | C8: Interior | D8: Alta
A9: AMB-08 | B9: Dormitorio 2 | C9: Interior | D9: Normal
A10: AMB-09 | B10: Dormitorio 3 | C10: Interior | D10: Normal
A11: AMB-10 | B11: Dormitorio 4 | C11: Interior | D11: Normal
A12: AMB-11 | B12: Dormitorio 5 | C12: Interior | D12: Normal
A13: AMB-12 | B13: Dormitorio 6 | C13: Interior | D13: Normal
... A36: AMB-35 | B36: Otro | C36: Interior | D36: Normal

Sheet CATEGORIAS
A1: Categoría | B1: Subcategoría
A2: Muebles | B2: Sofás
A3: Muebles | B3: Sillones
A4: Muebles | B4: Poltronas
A5: Muebles | B5: Mesas
A6: Muebles | B6: Mesas de comedor
A7: Muebles | B7: Mesas de luz
A8: Muebles | B8: Sillas
A9: Muebles | B9: Bancos
A10: Muebles | B10: Escritorios
A11: Muebles | B11: Camas
A12: Muebles | B12: Cómodas
... A47: Objetos varios | B47: Otros

Sheet CONFIGURACION
A1: Ambientes | B1: Categorías | C1: Subcategorías | D1: Estados artículo | E1: Estados venta | F1: Publicar | G1: Tipo de inventario | H1: Nivel de valor | I1: Formas de pago
A2: Casco / Casa principal | B2: Muebles | C2: Sofás | D2: Excelente | E2: Disponible | F2: Sí | G2: Individual | H2: Alto | I2: Efectivo
A3: Living principal | B3: Decoración | C3: Sillones | D3: Muy bueno | E3: Reservado | F3: No | G3: Conjunto | H3: Medio | I3: Transferencia
A4: Living secundario | B4: Iluminación | C4: Poltronas | D4: Bueno | E4: Vendido | G4: Lote | H4: Bajo | I4: Mercado Pago
A5: Comedor principal | B5: Cocina | C5: Mesas | D5: Regular | E5: Retirado | I5: Otro
A6: Comedor secundario | B6: Vajilla y cristalería | C6: Mesas de comedor | D6: Para reparar | E6: No vender
A7: Cocina | B7: Electrodomésticos | C7: Mesas de luz
A8: Dormitorio principal | B8: Tecnología | C8: Sillas
A9: Dormitorio 2 | B9: Textiles y ropa blanca | C9: Bancos
A10: Dormitorio 3 | B10: Exterior y jardín | C10: Escritorios
A11: Dormitorio 4 | B11: Herramientas | C11: Camas
A12: Dormitorio 5 | B12: Antigüedades | C12: Cómodas
A13: Dormitorio 6 | B13: Libros | C13: Placares
A14: Dormitorio 7 | B14: Arte y cuadros | C14: Bibliotecas
A15: Dormitorio 8 | B15: Objetos varios | C15: Aparadores
A16: Dormitorio 9 | B16: Lotes | C16: Baúles
A17: Dormitorio 10 | B17: Otros | C17: Espejos
A18: Baño 1 | C18: Cuadros
A19: Baño 2 | C19: Adornos
A20: Baño 3 | C20: Relojes
A21: Baño 4 | C21: Lámparas de mesa
A22: Baño 5 | C22: Lámparas de pie
A23: Baño 6 | C23: Arañas / Lámparas de techo
A24: Baño 7 | C24: Alfombras
A25: Baño 8 | C25: Cortinas
A26: Galería | C26: Vajilla
A27: Quincho | C27: Cristalería
A28: Parrilla | C28: Cubiertos
A29: Pileta | C29: Ollas
... A36: Otro | C36: Muebles de exterior
C37: Parrilla
C38: Pileta
C39: Herramientas de jardín
C40: Herramientas generales
C41: Ropa de cama
C42: Toallas
C43: Libros
C44: Antigüedades
C45: Obras de arte
C46: Lote de objetos
C47: Otros

Sheet INSTRUCCIONES FOTOS
A1: CÓMO CARGAR LAS FOTOS
A3: 1. | B3: En INVENTARIO, buscá la fila del producto.
A4: 2. | B4: En 'Foto principal (insertar en celda)', usá Excel: Insertar → Imágenes → Colocar en celda.
A5: 3. | B5: No uses una imagen flotante sobre la celda: tiene que quedar colocada DENTRO de la celda.
A6: 4. | B6: La hoja CATALOGO FERIA toma esa imagen automáticamente y la muestra en la columna Imagen.
A7: 5. | B7: Si cambiás la foto de INVENTARIO, el catálogo se actualiza al abrir/recalcular Excel.
